Workbook

Sheet Dashboard
A1: MUSIC CATALOG | INVESTMENT DASHBOARD
A3: KEY INVESTMENT METRICS
A5: DCF enterprise value | B5: =DCF!B12 -> 8817528.5
A6: Multiples valuation | B6: =Multiples!B7 -> 13283400
A7: Proposed purchase price | B7: =Acquisition!B7 -> 12176450
A8: Equity required | B8: =Acquisition!B12 -> 5053226.8
A9: Levered investor IRR | B9: =Acquisition!B33 -> 0.082039307
A10: Equity MOIC | B10: =Acquisition!B34 -> 2.1609894
A11: Unlevered investor IRR | B11: =Acquisition!B35 -> 0.078789766
A12: DCF premium / (discount) to price | B12: =DCF!B12/Acquisition!B7-1 -> -0.27585392
A15: INVESTMENT DECISION FRAMEWORK
A17: DCF vs purchase price | B17: =IF(B5>B7,"DCF ABOVE PRICE","PRICE ABOVE DCF") -> PRICE ABOVE DCF
A18: Model purpose | B18: Acquisition screening / scenario exploration
A19: Important limitation | B19: Illustrative, not an investment recommendation
A22: REVENUE TREND ($)
A24: Year | B24: =Forecast!B4 -> 2026 | C24: =Forecast!C4 -> 2027 | D24: =Forecast!D4 -> 2028 | E24: =Forecast!E4 -> 2029 | F24: =Forecast!F4 -> 2030 | G24: =Forecast!G4 -> 2031 | H24: =Forecast!H4 -> 2032 | I24: =Forecast!I4 -> 2033 | ... K24: =Forecast!K4 -> 2035
A25: Revenue | B25: =Forecast!B10 -> 1335000 | C25: =Forecast!C10 -> 1360748.5 | D25: =Forecast!D10 -> 1387263.9 | E25: =Forecast!E10 -> 1414565.1 | F25: =Forecast!F10 -> 1442671.6 | G25: =Forecast!G10 -> 1471603.6 | H25: =Forecast!H10 -> 1501381.8 | I25: =Forecast!I10 -> 1532027.5 | ... K25: =Forecast!K10 -> 1596010.4
A28: FIVE-YEAR ACQUISITION UNDERWRITING
A30: LTM NLS/NPS proxy (pre-tax) | B30: =Historical!D19 -> 1106950
A31: Five-year purchase TEV | B31: ='Sources & Uses'!B7 -> 18818150
A32: Five-year levered IRR | B32: ='5Y Underwriting'!B37 -> 0.035999276
A33: Five-year unlevered IRR | B33: ='5Y Underwriting'!B38 -> 0.057247364
A34: Five-year equity MOIC | B34: ='5Y Underwriting'!B39 -> 1.1930997
A35: Parity entry / exit check | B35: ='5Y Underwriting'!B43 -> PARITY
A36: DCF mid-year enterprise value | B36: =DCF!B12 -> 8817528.5
A39: INVESTMENT MODEL INTERPRETATION
A41: Five-year underwriting: LTM NLS/NPS proxy × entry multiple; levered / unlevered IRR; financing; exit parity.
A42: Ten-year DCF: after-tax unlevered FCF, mid-year discounting and year-end perpetual terminal value.
A43: All financial data and assumptions are hypothetical and for illustrative investment analysis only.

Sheet Assumptions
A1: MODEL INPUTS | HYPOTHETICAL DATA
A2: Blue = hypothetical inputs | green = cross-sheet references | model values in USD
A4: CATALOG & TRANSACTION ASSUMPTIONS
A5: Historical base year | B5: 2025
A6: Projection start year | B6: 2026
A7: Annual streaming growth | B7: 0.025
A8: Annual performance growth | B8: 0.01
A9: Annual mechanical growth | B9: -0.02
A10: Annual sync growth | B10: 0.035
A11: Annual other growth | B11: 0
A12: Royalty admin fee (% revenue) | B12: 0.12
A13: Other operating cost (% revenue) | B13: 0.035
A14: Tax rate (simplified) | B14: 0.25
A15: Unlevered discount rate / WACC proxy | B15: 0.105
A16: Terminal cash-flow growth rate | B16: -0.015
... A28: Annual sync growth (bull scenario) | B28: 0.2
A31: SOURCE & USE NOTES
A33: All blue cells are illustrative assumptions, NOT sourced market benchmarks.
A34: Replace with licensed royalty statements, contract economics, and transaction evidence.
A35: Cash flows reflect a simplified royalty-rights acquisition; no working capital/capex assumed.
A36: Terminal value assumes continuing rights and must be adjusted for term expirations.
A37: Interest tax shield and full accounting statements are not modeled.
A40: 5-YEAR CATALOG UNDERWRITING INPUTS
A42: Catalog type / rights basis | B42: Mixed rights (illustrative)
A43: Underwritten ownership share | B43: 1
A44: Five-year entry multiple (TEV / LTM NLS/NPS) | B44: 17
A45: Five-year exit multiple (TEV / Year 5 NLS/NPS) | B45: 17
A46: Five-year debt-to-capitalization | B46: 0.65
A47: Five-year interest rate | B47: 0.07
A48: Five-year initial transaction fees (% TEV) | B48: 0.015
A49: Five-year exit costs (% exit TEV) | B49: 0.02
A50: Debt amortization / year (% original debt) | B50: 0
A51: Exit after year | B51: 5
A52: Five-year earnings tax rate | B52: 0.25
A53: Five-year risk commentary | B53: Illustrative; risk / rights type should guide WACC, multiples and financing.

Sheet Historical
A1: HISTORICAL ROYALTY REVENUE
A3: REVENUE BY RIGHT / SOURCE
B4: 2023 | C4: 2024 | D4: 2025
A5: Streaming | B5: 650000 | C5: 720000 | D5: 780000
A6: Performance | B6: 180000 | C6: 195000 | D6: 210000
A7: Mechanical | B7: 120000 | C7: 115000 | D7: 110000
A8: Synchronization | B8: 90000 | C8: 140000 | D8: 160000
A9: Other | B9: 60000 | C9: 55000 | D9: 50000
A10: TOTAL ROYALTY REVENUE | B10: =SUM(B5:B9) -> 1100000 | C10: =SUM(C5:C9) -> 1225000 | D10: =SUM(D5:D9) -> 1310000
A11: YoY growth | C11: =IFERROR(C10/B10-1,0) -> 0.11363636 | D11: =IFERROR(D10/C10-1,0) -> 0.069387755
A13: Admin fees | B13: =-B10*Assumptions!$B$12 -> -132000 | C13: =-C10*Assumptions!$B$12 -> -147000 | D13: =-D10*Assumptions!$B$12 -> -157200
A14: Other operating costs | B14: =-B10*Assumptions!$B$13 -> -38500 | C14: =-C10*Assumptions!$B$13 -> -42875 | D14: =-D10*Assumptions!$B$13 -> -45850
A15: CASH FLOW BEFORE TAX | B15: =SUM(B10,B13:B14) -> 929500 | C15: =SUM(C10,C13:C14) -> 1035125 | D15: =SUM(D10,D13:D14) -> 1106950
A16: Taxes | B16: =-MAX(0,B15)*Assumptions!$B$14 -> -232375 | C16: =-MAX(0,C15)*Assumptions!$B$14 -> -258781.25 | D16: =-MAX(0,D15)*Assumptions!$B$14 -> -276737.5
A17: UNLEVERED AFTER-TAX CASH FLOW | B17: =SUM(B15:B16) -> 697125 | C17: =SUM(C15:C16) -> 776343.75 | D17: =SUM(D15:D16) -> 830212.5
A19: LTM NLS/NPS proxy (pre-tax, after admin and operating costs) | B19: =B15 -> 929500 | C19: =C15 -> 1035125 | D19: =D15 -> 1106950

Sheet Forecast
A1: 10-YEAR ROYALTY FORECAST
A3: REVENUE PROJECTION
B4: =Assumptions!$B$6+0 -> 2026 | C4: =Assumptions!$B$6+1 -> 2027 | D4: =Assumptions!$B$6+2 -> 2028 | E4: =Assumptions!$B$6+3 -> 2029 | F4: =Assumptions!$B$6+4 -> 2030 | G4: =Assumptions!$B$6+5 -> 2031 | H4: =Assumptions!$B$6+6 -> 2032 | I4: =Assumptions!$B$6+7 -> 2033 | J4: =Assumptions!$B$6+8 -> 2034 | K4: =Assumptions!$B$6+9 -> 2035
A5: Streaming | B5: =Historical!$D$5*(1+Assumptions!$B$7) -> 799500 | C5: =B5*(1+Assumptions!$B$7) -> 819487.5 | D5: =C5*(1+Assumptions!$B$7) -> 839974.69 | E5: =D5*(1+Assumptions!$B$7) -> 860974.05 | F5: =E5*(1+Assumptions!$B$7) -> 882498.41 | G5: =F5*(1+Assumptions!$B$7) -> 904560.87 | H5: =G5*(1+Assumptions!$B$7) -> 927174.89 | I5: =H5*(1+Assumptions!$B$7) -> 950354.26 | J5: =I5*(1+Assumptions!$B$7) -> 974113.12 | K5: =J5*(1+Assumptions!$B$7) -> 998465.94
A6: Performance | B6: =Historical!$D$6*(1+Assumptions!$B$8) -> 212100 | C6: =B6*(1+Assumptions!$B$8) -> 214221 | D6: =C6*(1+Assumptions!$B$8) -> 216363.21 | E6: =D6*(1+Assumptions!$B$8) -> 218526.84 | F6: =E6*(1+Assumptions!$B$8) -> 220712.11 | G6: =F6*(1+Assumptions!$B$8) -> 222919.23 | H6: =G6*(1+Assumptions!$B$8) -> 225148.42 | I6: =H6*(1+Assumptions!$B$8) -> 227399.91 | J6: =I6*(1+Assumptions!$B$8) -> 229673.91 | K6: =J6*(1+Assumptions!$B$8) -> 231970.65
A7: Mechanical | B7: =Historical!$D$7*(1+Assumptions!$B$9) -> 107800 | C7: =B7*(1+Assumptions!$B$9) -> 105644 | D7: =C7*(1+Assumptions!$B$9) -> 103531.12 | E7: =D7*(1+Assumptions!$B$9) -> 101460.5 | F7: =E7*(1+Assumptions!$B$9) -> 99431.288 | G7: =F7*(1+Assumptions!$B$9) -> 97442.662 | H7: =G7*(1+Assumptions!$B$9) -> 95493.809 | I7: =H7*(1+Assumptions!$B$9) -> 93583.932 | J7: =I7*(1+Assumptions!$B$9) -> 91712.254 | K7: =J7*(1+Assumptions!$B$9) -> 89878.009
A8: Synchronization | B8: =Historical!$D$8*(1+Assumptions!$B$10) -> 165600 | C8: =B8*(1+Assumptions!$B$10) -> 171396 | D8: =C8*(1+Assumptions!$B$10) -> 177394.86 | E8: =D8*(1+Assumptions!$B$10) -> 183603.68 | F8: =E8*(1+Assumptions!$B$10) -> 190029.81 | G8: =F8*(1+Assumptions!$B$10) -> 196680.85 | H8: =G8*(1+Assumptions!$B$10) -> 203564.68 | I8: =H8*(1+Assumptions!$B$10) -> 210689.45 | J8: =I8*(1+Assumptions!$B$10) -> 218063.58 | K8: =J8*(1+Assumptions!$B$10) -> 225695.8
A9: Other | B9: =Historical!$D$9*(1+Assumptions!$B$11) -> 50000 | C9: =B9*(1+Assumptions!$B$11) -> 50000 | D9: =C9*(1+Assumptions!$B$11) -> 50000 | E9: =D9*(1+Assumptions!$B$11) -> 50000 | F9: =E9*(1+Assumptions!$B$11) -> 50000 | G9: =F9*(1+Assumptions!$B$11) -> 50000 | H9: =G9*(1+Assumptions!$B$11) -> 50000 | I9: =H9*(1+Assumptions!$B$11) -> 50000 | J9: =I9*(1+Assumptions!$B$11) -> 50000 | K9: =J9*(1+Assumptions!$B$11) -> 50000
A10: TOTAL ROYALTY REVENUE | B10: =SUM(B5:B9) -> 1335000 | C10: =SUM(C5:C9) -> 1360748.5 | D10: =SUM(D5:D9) -> 1387263.9 | E10: =SUM(E5:E9) -> 1414565.1 | F10: =SUM(F5:F9) -> 1442671.6 | G10: =SUM(G5:G9) -> 1471603.6 | H10: =SUM(H5:H9) -> 1501381.8 | I10: =SUM(I5:I9) -> 1532027.5 | ... K10: =SUM(K5:K9) -> 1596010.4
A12: Administration fees | B12: =-B10*Assumptions!$B$12 -> -160200 | C12: =-C10*Assumptions!$B$12 -> -163289.82 | D12: =-D10*Assumptions!$B$12 -> -166471.67 | E12: =-E10*Assumptions!$B$12 -> -169747.81 | F12: =-F10*Assumptions!$B$12 -> -173120.59 | G12: =-G10*Assumptions!$B$12 -> -176592.43 | H12: =-H10*Assumptions!$B$12 -> -180165.82 | I12: =-I10*Assumptions!$B$12 -> -183843.31 | ... K12: =-K10*Assumptions!$B$12 -> -191521.25
A13: Operating costs | B13: =-B10*Assumptions!$B$13 -> -46725 | C13: =-C10*Assumptions!$B$13 -> -47626.197 | D13: =-D10*Assumptions!$B$13 -> -48554.236 | E13: =-E10*Assumptions!$B$13 -> -49509.778 | F13: =-F10*Assumptions!$B$13 -> -50493.506 | G13: =-G10*Assumptions!$B$13 -> -51506.126 | H13: =-H10*Assumptions!$B$13 -> -52548.363 | I13: =-I10*Assumptions!$B$13 -> -53620.964 | ... K13: =-K10*Assumptions!$B$13 -> -55860.364
A14: PRE-TAX CASH FLOW | B14: =SUM(B10:B13) -> 1128075 | C14: =SUM(C10:C13) -> 1149832.5 | D14: =SUM(D10:D13) -> 1172238 | E14: =SUM(E10:E13) -> 1195307.5 | F14: =SUM(F10:F13) -> 1219057.5 | G14: =SUM(G10:G13) -> 1243505.1 | H14: =SUM(H10:H13) -> 1268667.6 | I14: =SUM(I10:I13) -> 1294563.3 | ... K14: =SUM(K10:K13) -> 1348628.8
A16: Taxes | B16: =-MAX(0,B14)*Assumptions!$B$14 -> -282018.75 | C16: =-MAX(0,C14)*Assumptions!$B$14 -> -287458.12 | D16: =-MAX(0,D14)*Assumptions!$B$14 -> -293059.49 | E16: =-MAX(0,E14)*Assumptions!$B$14 -> -298826.87 | F16: =-MAX(0,F14)*Assumptions!$B$14 -> -304764.38 | G16: =-MAX(0,G14)*Assumptions!$B$14 -> -310876.26 | H16: =-MAX(0,H14)*Assumptions!$B$14 -> -317166.91 | I16: =-MAX(0,I14)*Assumptions!$B$14 -> -323640.82 | ... K16: =-MAX(0,K14)*Assumptions!$B$14 -> -337157.2
A17: UNLEVERED AFTER-TAX CASH FLOW | B17: =SUM(B14:B16) -> 846056.25 | C17: =SUM(C14:C16) -> 862374.36 | D17: =SUM(D14:D16) -> 879178.48 | E17: =SUM(E14:E16) -> 896480.62 | F17: =SUM(F14:F16) -> 914293.13 | G17: =SUM(G14:G16) -> 932628.79 | H17: =SUM(H14:H16) -> 951500.72 | I17: =SUM(I14:I16) -> 970922.46 | ... K17: =SUM(K14:K16) -> 1011471.6
A19: Present value of annual cash flow | B19: =B17/(1+Assumptions!$B$15)^(1-0.5) -> 804855.84 | C19: =C17/(1+Assumptions!$B$15)^(2-0.5) -> 742424.71 | D19: =D17/(1+Assumptions!$B$15)^(3-0.5) -> 684969.69 | E19: =E17/(1+Assumptions!$B$15)^(4-0.5) -> 632081.28 | F19: =F17/(1+Assumptions!$B$15)^(5-0.5) -> 583384.93 | G19: =G17/(1+Assumptions!$B$15)^(6-0.5) -> 538537.92 | H19: =H17/(1+Assumptions!$B$15)^(7-0.5) -> 497226.55 | I19: =I17/(1+Assumptions!$B$15)^(8-0.5) -> 459163.61 | J19: =J17/(1+Assumptions!$B$15)^(9-0.5) -> 424086.02 | K19: =K17/(1+Assumptions!$B$15)^(10-0.5) -> 391752.75
A21: Projected NLS/NPS proxy (pre-tax) | B21: =B14 -> 1128075 | C21: =C14 -> 1149832.5 | D21: =D14 -> 1172238 | E21: =E14 -> 1195307.5 | F21: =F14 -> 1219057.5 | G21: =G14 -> 1243505.1 | H21: =H14 -> 1268667.6 | I21: =I14 -> 1294563.3 | ... K21: =K14 -> 1348628.8

Sheet DCF
A1: DISCOUNTED CASH FLOW VALUATION
A3: ENTERPRISE VALUE BRIDGE
A5: PV of cash flows (mid-year convention) | B5: =SUM(Forecast!B19:K19) -> 5758483.3
A6: Year 10 cash flow | B6: =Forecast!K17 -> 1011471.6
A7: Terminal growth rate | B7: =Assumptions!B16 -> -0.015
A8: Discount rate | B8: =Assumptions!B15 -> 0.105
A9: Terminal value at year 10 | B9: =B6*(1+B7)/(B8-B7) -> 8302496
A10: PV of terminal value | B10: =B9/(1+B8)^10 -> 3059045.2
A12: DCF ENTERPRISE VALUE | B12: =SUM(B5,B10) -> 8817528.5
A14: 2025 normalized after-tax cash flow | B14: =Historical!D19 -> 1106950
A15: Implied DCF / LTM NLS/NPS proxy | B15: =IFERROR(B12/B14,0) -> 7.9656068
A17: Note: cash flows are simplified after-tax proxies; WACC and tax assumptions must be consistent.
A18: Illustrative perpetuity terminal value; validate rights duration and decay.

Sheet Multiples
A1: MULTIPLES & TRIANGULATION
A3: NORMALIZED LTM NLS/NPS PROXY VALUATION
A5: Normalized LTM NLS/NPS proxy (pre-tax) | B5: =Historical!D19 -> 1106950
A6: Selected TEV / LTM NLS/NPS multiple | B6: =Assumptions!B17 -> 12
A7: MULTIPLES-BASED ENTERPRISE VALUE | B7: =B5*B6 -> 13283400
A9: DCF enterprise value | B9: =DCF!B12 -> 8817528.5
A10: Difference: DCF less multiples | B10: =B9-B7 -> -4465871.5
A12: Low valuation (90% multiples) | B12: =B7*90% -> 11955060
A13: High valuation (110% DCF) | B13: =B9*110% -> 9699281.4
A16: Valuation uses LTM NLS/NPS capitalization multiples; the pre-tax earnings proxy is hypothetical and simplified.

Sheet Acquisition
A1: ACQUISITION FINANCING & INVESTOR RETURNS
A3: SOURCES & USES
A5: LTM NLS/NPS proxy (pre-tax) | B5: =Historical!D19 -> 1106950
A6: Purchase multiple | B6: =Assumptions!B18 -> 11
A7: Acquisition price | B7: =B5*B6 -> 12176450
A8: Transaction fees | B8: =B7*Assumptions!B24 -> 182646.75
A9: TOTAL INITIAL USES | B9: =SUM(B7:B8) -> 12359097
A11: Initial debt | B11: =B7*Assumptions!B19 -> 7305870
A12: INITIAL EQUITY | B12: =B9-B11 -> 5053226.8
A14: Debt percentage | B14: =Assumptions!B19 -> 0.6
A15: Annual interest rate | B15: =Assumptions!B20 -> 0.075
A16: Amortization (% original debt) | B16: =Assumptions!B21 -> 0.05
A19: EXIT AND CASH DISTRIBUTIONS
A21: Projection year | B21: 0 | C21: =Forecast!B4 -> 2026 | D21: =Forecast!C4 -> 2027 | E21: =Forecast!D4 -> 2028 | F21: =Forecast!E4 -> 2029 | G21: =Forecast!F4 -> 2030 | H21: =Forecast!G4 -> 2031 | I21: =Forecast!H4 -> 2032 | J21: =Forecast!I4 -> 2033 | ... L21: =Forecast!K4 -> 2035
A22: After-tax unlevered cash flow (operating) | C22: =Forecast!B17 -> 846056.25 | D22: =Forecast!C17 -> 862374.36 | E22: =Forecast!D17 -> 879178.48 | F22: =Forecast!E17 -> 896480.62 | G22: =Forecast!F17 -> 914293.13 | H22: =Forecast!G17 -> 932628.79 | I22: =Forecast!H17 -> 951500.72 | J22: =Forecast!I17 -> 970922.46 | ... L22: =Forecast!K17 -> 1011471.6
A23: Opening debt | C23: =$B$11 -> 7305870 | D23: =C26 -> 6940576.5 | E23: =D26 -> 6575283 | F23: =E26 -> 6209989.5 | G23: =F26 -> 5844696 | H23: =G26 -> 5479402.5 | I23: =H26 -> 5114109 | J23: =I26 -> 4748815.5 | K23: =J26 -> 4383522 | L23: =K26 -> 4018228.5
A24: Interest expense | C24: =-C23*$B$15 -> -547940.25 | D24: =-D23*$B$15 -> -520543.24 | E24: =-E23*$B$15 -> -493146.22 | F24: =-F23*$B$15 -> -465749.21 | G24: =-G23*$B$15 -> -438352.2 | H24: =-H23*$B$15 -> -410955.19 | I24: =-I23*$B$15 -> -383558.17 | J24: =-J23*$B$15 -> -356161.16 | ... L24: =-L23*$B$15 -> -301367.14
A25: Principal repayment | C25: =-MIN(C23,$B$11*$B$16) -> -365293.5 | D25: =-MIN(D23,$B$11*$B$16) -> -365293.5 | E25: =-MIN(E23,$B$11*$B$16) -> -365293.5 | F25: =-MIN(F23,$B$11*$B$16) -> -365293.5 | G25: =-MIN(G23,$B$11*$B$16) -> -365293.5 | H25: =-MIN(H23,$B$11*$B$16) -> -365293.5 | I25: =-MIN(I23,$B$11*$B$16) -> -365293.5 | J25: =-MIN(J23,$B$11*$B$16) -> -365293.5 | ... L25: =-MIN(L23,$B$11*$B$16) -> -365293.5
A26: Closing debt | C26: =SUM(C23,C25) -> 6940576.5 | D26: =SUM(D23,D25) -> 6575283 | E26: =SUM(E23,E25) -> 6209989.5 | F26: =SUM(F23,F25) -> 5844696 | G26: =SUM(G23,G25) -> 5479402.5 | H26: =SUM(H23,H25) -> 5114109 | I26: =SUM(I23,I25) -> 4748815.5 | J26: =SUM(J23,J25) -> 4383522 | ... L26: =SUM(L23,L25) -> 3652935
A27: Cash distributed to equity | C27: =SUM(C22,C24:C25) -> -67177.5 | D27: =SUM(D22,D24:D25) -> -23462.376 | E27: =SUM(E22,E24:E25) -> 20738.757 | F27: =SUM(F22,F24:F25) -> 65437.903 | G27: =SUM(G22,G24:G25) -> 110647.43 | H27: =SUM(H22,H24:H25) -> 156380.1 | I27: =SUM(I22,I24:I25) -> 202649.04 | J27: =SUM(J22,J24:J25) -> 249467.8 | ... L27: =SUM(L22,L24:L25) -> 344810.95
A28: Exit TEV (year-10 NLS/NPS multiple) | C28: =0 -> 0 | D28: =0 -> 0 | E28: =0 -> 0 | F28: =0 -> 0 | G28: =0 -> 0 | H28: =0 -> 0 | I28: =0 -> 0 | J28: =0 -> 0 | K28: =0 -> 0 | L28: =Forecast!K21*Assumptions!$B$22 -> 13486288
A29: Exit fees | C29: =-C28*Assumptions!$B$23 -> 0 | D29: =-D28*Assumptions!$B$23 -> 0 | E29: =-E28*Assumptions!$B$23 -> 0 | F29: =-F28*Assumptions!$B$23 -> 0 | G29: =-G28*Assumptions!$B$23 -> 0 | H29: =-H28*Assumptions!$B$23 -> 0 | I29: =-I28*Assumptions!$B$23 -> 0 | J29: =-J28*Assumptions!$B$23 -> 0 | ... L29: =-L28*Assumptions!$B$23 -> -269725.76
A30: Exit equity proceeds | C30: =0 -> 0 | D30: =0 -> 0 | E30: =0 -> 0 | F30: =0 -> 0 | G30: =0 -> 0 | H30: =0 -> 0 | I30: =0 -> 0 | J30: =0 -> 0 | K30: =0 -> 0 | L30: =SUM(L28:L29)-L26 -> 9563627.1
A31: TOTAL EQUITY CASH FLOW | B31: =-B12 -> -5053226.8 | C31: =SUM(C27,C30) -> -67177.5 | D31: =SUM(D27,D30) -> -23462.376 | E31: =SUM(E27,E30) -> 20738.757 | F31: =SUM(F27,F30) -> 65437.903 | G31: =SUM(G27,G30) -> 110647.43 | H31: =SUM(H27,H30) -> 156380.1 | I31: =SUM(I27,I30) -> 202649.04 | J31: =SUM(J27,J30) -> 249467.8 | ... L31: =SUM(L27,L30) -> 9908438.1
A33: Levered IRR | B33: =IRR(B31:L31) -> 0.082039307
A34: Equity MOIC | B34: =SUM(C31:L31)/-B31 -> 2.1609894
A35: Unlevered IRR | B35: =IRR(B37:L37) -> 0.078789766
A37: Unlevered investor cash flows (after-tax) | B37: =-B9 -> -12359097 | C37: =C22+C28+C29 -> 846056.25 | D37: =D22+D28+D29 -> 862374.36 | E37: =E22+E28+E29 -> 879178.48 | F37: =F22+F28+F29 -> 896480.62 | G37: =G22+G28+G29 -> 914293.13 | H37: =H22+H28+H29 -> 932628.79 | I37: =I22+I28+I29 -> 951500.72 | J37: =J22+J28+J29 -> 970922.46 | ... L37: =L22+L28+L29 -> 14228034

Sheet Sensitivities
A1: VALUATION & RETURN SENSITIVITIES
A3: DCF VALUE | DISCOUNT RATE × TERMINAL GROWTH
A5: Discount rate ↓ / terminal growth →
C6: -0.035 | D6: -0.025 | E6: -0.015 | F6: -0.005 | G6: 0.005
B7: 0.085 | C7: =IFERROR((Forecast!$B$17/(1+$B7)^(1-0.5)+Forecast!$C$17/(1+$B7)^(2-0.5)+Forecast!$D$17/(1+$B7)^(3-0.5)+Forecast!$E$17/(1+$B7)^(4-0.5)+Forecast!$F$17/(1+$B7)^(5-0.5)+Forecast!$G$17/(1+$B7)^(6-0.5)+Forecast!$H$17/(1+$B7)^(7-0.5)+Forecast!$I$17/(1+$B7)^(8-0.5)+Forecast!$J$17/(1+$B7)^(9-0.5)+Forecast!$K$17/(1+$B7)^(10-0.5))+Forecast!$K$17*(1+C$6)/($B7-C$6)/(1+$B7)^10,0) -> 9840174.7 | D7: =IFERROR((Forecast!$B$17/(1+$B7)^(1-0.5)+Forecast!$C$17/(1+$B7)^(2-0.5)+Forecast!$D$17/(1+$B7)^(3-0.5)+Forecast!$E$17/(1+$B7)^(4-0.5)+Forecast!$F$17/(1+$B7)^(5-0.5)+Forecast!$G$17/(1+$B7)^(6-0.5)+Forecast!$H$17/(1+$B7)^(7-0.5)+Forecast!$I$17/(1+$B7)^(8-0.5)+Forecast!$J$17/(1+$B7)^(9-0.5)+Forecast!$K$17/(1+$B7)^(10-0.5))+Forecast!$K$17*(1+D$6)/($B7-D$6)/(1+$B7)^10,0) -> 10207890 | E7: =IFERROR((Forecast!$B$17/(1+$B7)^(1-0.5)+Forecast!$C$17/(1+$B7)^(2-0.5)+Forecast!$D$17/(1+$B7)^(3-0.5)+Forecast!$E$17/(1+$B7)^(4-0.5)+Forecast!$F$17/(1+$B7)^(5-0.5)+Forecast!$G$17/(1+$B7)^(6-0.5)+Forecast!$H$17/(1+$B7)^(7-0.5)+Forecast!$I$17/(1+$B7)^(8-0.5)+Forecast!$J$17/(1+$B7)^(9-0.5)+Forecast!$K$17/(1+$B7)^(10-0.5))+Forecast!$K$17*(1+E$6)/($B7-E$6)/(1+$B7)^10,0) -> 10649149 | F7: =IFERROR((Forecast!$B$17/(1+$B7)^(1-0.5)+Forecast!$C$17/(1+$B7)^(2-0.5)+Forecast!$D$17/(1+$B7)^(3-0.5)+Forecast!$E$17/(1+$B7)^(4-0.5)+Forecast!$F$17/(1+$B7)^(5-0.5)+Forecast!$G$17/(1+$B7)^(6-0.5)+Forecast!$H$17/(1+$B7)^(7-0.5)+Forecast!$I$17/(1+$B7)^(8-0.5)+Forecast!$J$17/(1+$B7)^(9-0.5)+Forecast!$K$17/(1+$B7)^(10-0.5))+Forecast!$K$17*(1+F$6)/($B7-F$6)/(1+$B7)^10,0) -> 11188465 | G7: =IFERROR((Forecast!$B$17/(1+$B7)^(1-0.5)+Forecast!$C$17/(1+$B7)^(2-0.5)+Forecast!$D$17/(1+$B7)^(3-0.5)+Forecast!$E$17/(1+$B7)^(4-0.5)+Forecast!$F$17/(1+$B7)^(5-0.5)+Forecast!$G$17/(1+$B7)^(6-0.5)+Forecast!$H$17/(1+$B7)^(7-0.5)+Forecast!$I$17/(1+$B7)^(8-0.5)+Forecast!$J$17/(1+$B7)^(9-0.5)+Forecast!$K$17/(1+$B7)^(10-0.5))+Forecast!$K$17*(1+G$6)/($B7-G$6)/(1+$B7)^10,0) -> 11862611
B8: 0.095 | C8: =IFERROR((Forecast!$B$17/(1+$B8)^(1-0.5)+Forecast!$C$17/(1+$B8)^(2-0.5)+Forecast!$D$17/(1+$B8)^(3-0.5)+Forecast!$E$17/(1+$B8)^(4-0.5)+Forecast!$F$17/(1+$B8)^(5-0.5)+Forecast!$G$17/(1+$B8)^(6-0.5)+Forecast!$H$17/(1+$B8)^(7-0.5)+Forecast!$I$17/(1+$B8)^(8-0.5)+Forecast!$J$17/(1+$B8)^(9-0.5)+Forecast!$K$17/(1+$B8)^(10-0.5))+Forecast!$K$17*(1+C$6)/($B8-C$6)/(1+$B8)^10,0) -> 9022248.2 | D8: =IFERROR((Forecast!$B$17/(1+$B8)^(1-0.5)+Forecast!$C$17/(1+$B8)^(2-0.5)+Forecast!$D$17/(1+$B8)^(3-0.5)+Forecast!$E$17/(1+$B8)^(4-0.5)+Forecast!$F$17/(1+$B8)^(5-0.5)+Forecast!$G$17/(1+$B8)^(6-0.5)+Forecast!$H$17/(1+$B8)^(7-0.5)+Forecast!$I$17/(1+$B8)^(8-0.5)+Forecast!$J$17/(1+$B8)^(9-0.5)+Forecast!$K$17/(1+$B8)^(10-0.5))+Forecast!$K$17*(1+D$6)/($B8-D$6)/(1+$B8)^10,0) -> 9308733.3 | E8: =IFERROR((Forecast!$B$17/(1+$B8)^(1-0.5)+Forecast!$C$17/(1+$B8)^(2-0.5)+Forecast!$D$17/(1+$B8)^(3-0.5)+Forecast!$E$17/(1+$B8)^(4-0.5)+Forecast!$F$17/(1+$B8)^(5-0.5)+Forecast!$G$17/(1+$B8)^(6-0.5)+Forecast!$H$17/(1+$B8)^(7-0.5)+Forecast!$I$17/(1+$B8)^(8-0.5)+Forecast!$J$17/(1+$B8)^(9-0.5)+Forecast!$K$17/(1+$B8)^(10-0.5))+Forecast!$K$17*(1+E$6)/($B8-E$6)/(1+$B8)^10,0) -> 9647306.6 | F8: =IFERROR((Forecast!$B$17/(1+$B8)^(1-0.5)+Forecast!$C$17/(1+$B8)^(2-0.5)+Forecast!$D$17/(1+$B8)^(3-0.5)+Forecast!$E$17/(1+$B8)^(4-0.5)+Forecast!$F$17/(1+$B8)^(5-0.5)+Forecast!$G$17/(1+$B8)^(6-0.5)+Forecast!$H$17/(1+$B8)^(7-0.5)+Forecast!$I$17/(1+$B8)^(8-0.5)+Forecast!$J$17/(1+$B8)^(9-0.5)+Forecast!$K$17/(1+$B8)^(10-0.5))+Forecast!$K$17*(1+F$6)/($B8-F$6)/(1+$B8)^10,0) -> 10053594 | G8: =IFERROR((Forecast!$B$17/(1+$B8)^(1-0.5)+Forecast!$C$17/(1+$B8)^(2-0.5)+Forecast!$D$17/(1+$B8)^(3-0.5)+Forecast!$E$17/(1+$B8)^(4-0.5)+Forecast!$F$17/(1+$B8)^(5-0.5)+Forecast!$G$17/(1+$B8)^(6-0.5)+Forecast!$H$17/(1+$B8)^(7-0.5)+Forecast!$I$17/(1+$B8)^(8-0.5)+Forecast!$J$17/(1+$B8)^(9-0.5)+Forecast!$K$17/(1+$B8)^(10-0.5))+Forecast!$K$17*(1+G$6)/($B8-G$6)/(1+$B8)^10,0) -> 10550169
B9: 0.105 | C9: =IFERROR((Forecast!$B$17/(1+$B9)^(1-0.5)+Forecast!$C$17/(1+$B9)^(2-0.5)+Forecast!$D$17/(1+$B9)^(3-0.5)+Forecast!$E$17/(1+$B9)^(4-0.5)+Forecast!$F$17/(1+$B9)^(5-0.5)+Forecast!$G$17/(1+$B9)^(6-0.5)+Forecast!$H$17/(1+$B9)^(7-0.5)+Forecast!$I$17/(1+$B9)^(8-0.5)+Forecast!$J$17/(1+$B9)^(9-0.5)+Forecast!$K$17/(1+$B9)^(10-0.5))+Forecast!$K$17*(1+C$6)/($B9-C$6)/(1+$B9)^10,0) -> 8327282.7 | D9: =IFERROR((Forecast!$B$17/(1+$B9)^(1-0.5)+Forecast!$C$17/(1+$B9)^(2-0.5)+Forecast!$D$17/(1+$B9)^(3-0.5)+Forecast!$E$17/(1+$B9)^(4-0.5)+Forecast!$F$17/(1+$B9)^(5-0.5)+Forecast!$G$17/(1+$B9)^(6-0.5)+Forecast!$H$17/(1+$B9)^(7-0.5)+Forecast!$I$17/(1+$B9)^(8-0.5)+Forecast!$J$17/(1+$B9)^(9-0.5)+Forecast!$K$17/(1+$B9)^(10-0.5))+Forecast!$K$17*(1+D$6)/($B9-D$6)/(1+$B9)^10,0) -> 8553550 | E9: =IFERROR((Forecast!$B$17/(1+$B9)^(1-0.5)+Forecast!$C$17/(1+$B9)^(2-0.5)+Forecast!$D$17/(1+$B9)^(3-0.5)+Forecast!$E$17/(1+$B9)^(4-0.5)+Forecast!$F$17/(1+$B9)^(5-0.5)+Forecast!$G$17/(1+$B9)^(6-0.5)+Forecast!$H$17/(1+$B9)^(7-0.5)+Forecast!$I$17/(1+$B9)^(8-0.5)+Forecast!$J$17/(1+$B9)^(9-0.5)+Forecast!$K$17/(1+$B9)^(10-0.5))+Forecast!$K$17*(1+E$6)/($B9-E$6)/(1+$B9)^10,0) -> 8817528.5 | F9: =IFERROR((Forecast!$B$17/(1+$B9)^(1-0.5)+Forecast!$C$17/(1+$B9)^(2-0.5)+Forecast!$D$17/(1+$B9)^(3-0.5)+Forecast!$E$17/(1+$B9)^(4-0.5)+Forecast!$F$17/(1+$B9)^(5-0.5)+Forecast!$G$17/(1+$B9)^(6-0.5)+Forecast!$H$17/(1+$B9)^(7-0.5)+Forecast!$I$17/(1+$B9)^(8-0.5)+Forecast!$J$17/(1+$B9)^(9-0.5)+Forecast!$K$17/(1+$B9)^(10-0.5))+Forecast!$K$17*(1+F$6)/($B9-F$6)/(1+$B9)^10,0) -> 9129503.1 | G9: =IFERROR((Forecast!$B$17/(1+$B9)^(1-0.5)+Forecast!$C$17/(1+$B9)^(2-0.5)+Forecast!$D$17/(1+$B9)^(3-0.5)+Forecast!$E$17/(1+$B9)^(4-0.5)+Forecast!$F$17/(1+$B9)^(5-0.5)+Forecast!$G$17/(1+$B9)^(6-0.5)+Forecast!$H$17/(1+$B9)^(7-0.5)+Forecast!$I$17/(1+$B9)^(8-0.5)+Forecast!$J$17/(1+$B9)^(9-0.5)+Forecast!$K$17/(1+$B9)^(10-0.5))+Forecast!$K$17*(1+G$6)/($B9-G$6)/(1+$B9)^10,0) -> 9503872.7
B10: 0.115 | C10: =IFERROR((Forecast!$B$17/(1+$B10)^(1-0.5)+Forecast!$C$17/(1+$B10)^(2-0.5)+Forecast!$D$17/(1+$B10)^(3-0.5)+Forecast!$E$17/(1+$B10)^(4-0.5)+Forecast!$F$17/(1+$B10)^(5-0.5)+Forecast!$G$17/(1+$B10)^(6-0.5)+Forecast!$H$17/(1+$B10)^(7-0.5)+Forecast!$I$17/(1+$B10)^(8-0.5)+Forecast!$J$17/(1+$B10)^(9-0.5)+Forecast!$K$17/(1+$B10)^(10-0.5))+Forecast!$K$17*(1+C$6)/($B10-C$6)/(1+$B10)^10,0) -> 7730129.7 | D10: =IFERROR((Forecast!$B$17/(1+$B10)^(1-0.5)+Forecast!$C$17/(1+$B10)^(2-0.5)+Forecast!$D$17/(1+$B10)^(3-0.5)+Forecast!$E$17/(1+$B10)^(4-0.5)+Forecast!$F$17/(1+$B10)^(5-0.5)+Forecast!$G$17/(1+$B10)^(6-0.5)+Forecast!$H$17/(1+$B10)^(7-0.5)+Forecast!$I$17/(1+$B10)^(8-0.5)+Forecast!$J$17/(1+$B10)^(9-0.5)+Forecast!$K$17/(1+$B10)^(10-0.5))+Forecast!$K$17*(1+D$6)/($B10-D$6)/(1+$B10)^10,0) -> 7910955.6 | E10: =IFERROR((Forecast!$B$17/(1+$B10)^(1-0.5)+Forecast!$C$17/(1+$B10)^(2-0.5)+Forecast!$D$17/(1+$B10)^(3-0.5)+Forecast!$E$17/(1+$B10)^(4-0.5)+Forecast!$F$17/(1+$B10)^(5-0.5)+Forecast!$G$17/(1+$B10)^(6-0.5)+Forecast!$H$17/(1+$B10)^(7-0.5)+Forecast!$I$17/(1+$B10)^(8-0.5)+Forecast!$J$17/(1+$B10)^(9-0.5)+Forecast!$K$17/(1+$B10)^(10-0.5))+Forecast!$K$17*(1+E$6)/($B10-E$6)/(1+$B10)^10,0) -> 8119600.8 | F10: =IFERROR((Forecast!$B$17/(1+$B10)^(1-0.5)+Forecast!$C$17/(1+$B10)^(2-0.5)+Forecast!$D$17/(1+$B10)^(3-0.5)+Forecast!$E$17/(1+$B10)^(4-0.5)+Forecast!$F$17/(1+$B10)^(5-0.5)+Forecast!$G$17/(1+$B10)^(6-0.5)+Forecast!$H$17/(1+$B10)^(7-0.5)+Forecast!$I$17/(1+$B10)^(8-0.5)+Forecast!$J$17/(1+$B10)^(9-0.5)+Forecast!$K$17/(1+$B10)^(10-0.5))+Forecast!$K$17*(1+F$6)/($B10-F$6)/(1+$B10)^10,0) -> 8363020.3 | G10: =IFERROR((Forecast!$B$17/(1+$B10)^(1-0.5)+Forecast!$C$17/(1+$B10)^(2-0.5)+Forecast!$D$17/(1+$B10)^(3-0.5)+Forecast!$E$17/(1+$B10)^(4-0.5)+Forecast!$F$17/(1+$B10)^(5-0.5)+Forecast!$G$17/(1+$B10)^(6-0.5)+Forecast!$H$17/(1+$B10)^(7-0.5)+Forecast!$I$17/(1+$B10)^(8-0.5)+Forecast!$J$17/(1+$B10)^(9-0.5)+Forecast!$K$17/(1+$B10)^(10-0.5))+Forecast!$K$17*(1+G$6)/($B10-G$6)/(1+$B10)^10,0) -> 8650697.8
B11: 0.125 | C11: =IFERROR((Forecast!$B$17/(1+$B11)^(1-0.5)+Forecast!$C$17/(1+$B11)^(2-0.5)+Forecast!$D$17/(1+$B11)^(3-0.5)+Forecast!$E$17/(1+$B11)^(4-0.5)+Forecast!$F$17/(1+$B11)^(5-0.5)+Forecast!$G$17/(1+$B11)^(6-0.5)+Forecast!$H$17/(1+$B11)^(7-0.5)+Forecast!$I$17/(1+$B11)^(8-0.5)+Forecast!$J$17/(1+$B11)^(9-0.5)+Forecast!$K$17/(1+$B11)^(10-0.5))+Forecast!$K$17*(1+C$6)/($B11-C$6)/(1+$B11)^10,0) -> 7211986.2 | D11: =IFERROR((Forecast!$B$17/(1+$B11)^(1-0.5)+Forecast!$C$17/(1+$B11)^(2-0.5)+Forecast!$D$17/(1+$B11)^(3-0.5)+Forecast!$E$17/(1+$B11)^(4-0.5)+Forecast!$F$17/(1+$B11)^(5-0.5)+Forecast!$G$17/(1+$B11)^(6-0.5)+Forecast!$H$17/(1+$B11)^(7-0.5)+Forecast!$I$17/(1+$B11)^(8-0.5)+Forecast!$J$17/(1+$B11)^(9-0.5)+Forecast!$K$17/(1+$B11)^(10-0.5))+Forecast!$K$17*(1+D$6)/($B11-D$6)/(1+$B11)^10,0) -> 7357991.8 | E11: =IFERROR((Forecast!$B$17/(1+$B11)^(1-0.5)+Forecast!$C$17/(1+$B11)^(2-0.5)+Forecast!$D$17/(1+$B11)^(3-0.5)+Forecast!$E$17/(1+$B11)^(4-0.5)+Forecast!$F$17/(1+$B11)^(5-0.5)+Forecast!$G$17/(1+$B11)^(6-0.5)+Forecast!$H$17/(1+$B11)^(7-0.5)+Forecast!$I$17/(1+$B11)^(8-0.5)+Forecast!$J$17/(1+$B11)^(9-0.5)+Forecast!$K$17/(1+$B11)^(10-0.5))+Forecast!$K$17*(1+E$6)/($B11-E$6)/(1+$B11)^10,0) -> 7524855.5 | F11: =IFERROR((Forecast!$B$17/(1+$B11)^(1-0.5)+Forecast!$C$17/(1+$B11)^(2-0.5)+Forecast!$D$17/(1+$B11)^(3-0.5)+Forecast!$E$17/(1+$B11)^(4-0.5)+Forecast!$F$17/(1+$B11)^(5-0.5)+Forecast!$G$17/(1+$B11)^(6-0.5)+Forecast!$H$17/(1+$B11)^(7-0.5)+Forecast!$I$17/(1+$B11)^(8-0.5)+Forecast!$J$17/(1+$B11)^(9-0.5)+Forecast!$K$17/(1+$B11)^(10-0.5))+Forecast!$K$17*(1+F$6)/($B11-F$6)/(1+$B11)^10,0) -> 7717390.4 | G11: =IFERROR((Forecast!$B$17/(1+$B11)^(1-0.5)+Forecast!$C$17/(1+$B11)^(2-0.5)+Forecast!$D$17/(1+$B11)^(3-0.5)+Forecast!$E$17/(1+$B11)^(4-0.5)+Forecast!$F$17/(1+$B11)^(5-0.5)+Forecast!$G$17/(1+$B11)^(6-0.5)+Forecast!$H$17/(1+$B11)^(7-0.5)+Forecast!$I$17/(1+$B11)^(8-0.5)+Forecast!$J$17/(1+$B11)^(9-0.5)+Forecast!$K$17/(1+$B11)^(10-0.5))+Forecast!$K$17*(1+G$6)/($B11-G$6)/(1+$B11)^10,0) -> 7942014.6
A14: EXIT EQUITY PROCEEDS | NLS/NPS ENTRY × EXIT MULTIPLES
A16: Entry multiple ↓ / exit multiple →
C17: 8 | D17: 9 | E17: 10 | F17: 11 | G17: 12
B18: 9 | C18: =Forecast!$K$21*C$17*(1-Assumptions!$B$23)-MAX(0,Historical!$D$19*$B18*Assumptions!$B$19*(1-10*Assumptions!$B$21)) -> 7584484.7 | D18: =Forecast!$K$21*D$17*(1-Assumptions!$B$23)-MAX(0,Historical!$D$19*$B18*Assumptions!$B$19*(1-10*Assumptions!$B$21)) -> 8906140.9 | E18: =Forecast!$K$21*E$17*(1-Assumptions!$B$23)-MAX(0,Historical!$D$19*$B18*Assumptions!$B$19*(1-10*Assumptions!$B$21)) -> 10227797 | F18: =Forecast!$K$21*F$17*(1-Assumptions!$B$23)-MAX(0,Historical!$D$19*$B18*Assumptions!$B$19*(1-10*Assumptions!$B$21)) -> 11549453 | G18: =Forecast!$K$21*G$17*(1-Assumptions!$B$23)-MAX(0,Historical!$D$19*$B18*Assumptions!$B$19*(1-10*Assumptions!$B$21)) -> 12871110
B19: 10 | C19: =Forecast!$K$21*C$17*(1-Assumptions!$B$23)-MAX(0,Historical!$D$19*$B19*Assumptions!$B$19*(1-10*Assumptions!$B$21)) -> 7252399.7 | D19: =Forecast!$K$21*D$17*(1-Assumptions!$B$23)-MAX(0,Historical!$D$19*$B19*Assumptions!$B$19*(1-10*Assumptions!$B$21)) -> 8574055.9 | E19: =Forecast!$K$21*E$17*(1-Assumptions!$B$23)-MAX(0,Historical!$D$19*$B19*Assumptions!$B$19*(1-10*Assumptions!$B$21)) -> 9895712.1 | F19: =Forecast!$K$21*F$17*(1-Assumptions!$B$23)-MAX(0,Historical!$D$19*$B19*Assumptions!$B$19*(1-10*Assumptions!$B$21)) -> 11217368 | G19: =Forecast!$K$21*G$17*(1-Assumptions!$B$23)-MAX(0,Historical!$D$19*$B19*Assumptions!$B$19*(1-10*Assumptions!$B$21)) -> 12539025
B20: 11 | C20: =Forecast!$K$21*C$17*(1-Assumptions!$B$23)-MAX(0,Historical!$D$19*$B20*Assumptions!$B$19*(1-10*Assumptions!$B$21)) -> 6920314.7 | D20: =Forecast!$K$21*D$17*(1-Assumptions!$B$23)-MAX(0,Historical!$D$19*$B20*Assumptions!$B$19*(1-10*Assumptions!$B$21)) -> 8241970.9 | E20: =Forecast!$K$21*E$17*(1-Assumptions!$B$23)-MAX(0,Historical!$D$19*$B20*Assumptions!$B$19*(1-10*Assumptions!$B$21)) -> 9563627.1 | F20: =Forecast!$K$21*F$17*(1-Assumptions!$B$23)-MAX(0,Historical!$D$19*$B20*Assumptions!$B$19*(1-10*Assumptions!$B$21)) -> 10885283 | G20: =Forecast!$K$21*G$17*(1-Assumptions!$B$23)-MAX(0,Historical!$D$19*$B20*Assumptions!$B$19*(1-10*Assumptions!$B$21)) -> 12206940
B21: 12 | C21: =Forecast!$K$21*C$17*(1-Assumptions!$B$23)-MAX(0,Historical!$D$19*$B21*Assumptions!$B$19*(1-10*Assumptions!$B$21)) -> 6588229.7 | D21: =Forecast!$K$21*D$17*(1-Assumptions!$B$23)-MAX(0,Historical!$D$19*$B21*Assumptions!$B$19*(1-10*Assumptions!$B$21)) -> 7909885.9 | E21: =Forecast!$K$21*E$17*(1-Assumptions!$B$23)-MAX(0,Historical!$D$19*$B21*Assumptions!$B$19*(1-10*Assumptions!$B$21)) -> 9231542.1 | F21: =Forecast!$K$21*F$17*(1-Assumptions!$B$23)-MAX(0,Historical!$D$19*$B21*Assumptions!$B$19*(1-10*Assumptions!$B$21)) -> 10553198 | G21: =Forecast!$K$21*G$17*(1-Assumptions!$B$23)-MAX(0,Historical!$D$19*$B21*Assumptions!$B$19*(1-10*Assumptions!$B$21)) -> 11874855
B22: 13 | C22: =Forecast!$K$21*C$17*(1-Assumptions!$B$23)-MAX(0,Historical!$D$19*$B22*Assumptions!$B$19*(1-10*Assumptions!$B$21)) -> 6256144.7 | D22: =Forecast!$K$21*D$17*(1-Assumptions!$B$23)-MAX(0,Historical!$D$19*$B22*Assumptions!$B$19*(1-10*Assumptions!$B$21)) -> 7577800.9 | E22: =Forecast!$K$21*E$17*(1-Assumptions!$B$23)-MAX(0,Historical!$D$19*$B22*Assumptions!$B$19*(1-10*Assumptions!$B$21)) -> 8899457.1 | F22: =Forecast!$K$21*F$17*(1-Assumptions!$B$23)-MAX(0,Historical!$D$19*$B22*Assumptions!$B$19*(1-10*Assumptions!$B$21)) -> 10221113 | G22: =Forecast!$K$21*G$17*(1-Assumptions!$B$23)-MAX(0,Historical!$D$19*$B22*Assumptions!$B$19*(1-10*Assumptions!$B$21)) -> 11542770
A25: Second grid shows exit equity proceeds, not IRR; annual distributions are in Acquisition.

Sheet Rights Basis
A1: RIGHTS & EARNINGS BRIDGE
A2: Recorded music NLS / publishing NPS are distinct. Mixed royalty stream here is an illustrative cash-flow proxy.
A4: MODEL INTERPRETATION
A6: Rights underwritten | B6: =Assumptions!B42 -> Mixed rights (illustrative)
A7: Acquired ownership / participation | B7: =Assumptions!B43 -> 1
A8: LTM total royalty receipts ($) | B8: =Historical!D10 -> 1310000
A9: Less: administration and costs ($) | B9: =SUM(Historical!D13:D14) -> -203050
A10: LTM NLS/NPS proxy before tax ($) | B10: =Historical!D19 -> 1106950
A11: LTM attributable share ($) | B11: =B10*B7 -> 1106950
A12: After-tax annual operating cash flow ($) | B12: =Historical!D17 -> 830212.5
A14: Proxy multiple method | B14: Pre-tax NLS/NPS proxy; not the same as after-tax FCF multiple
A15: Rights caveat | B15: Replace model with contractual statements for master NLS or publisher NPS before live underwriting.
A16: Forecast caveat | B16: Sync is episodic; smooth growth here is only an illustrative assumption.
A17: Valuation caveat | B17: Exit multiple uses year-5/10 pre-tax proxy, DCF discounts after-tax cash flow.
A20: ILLUSTRATIVE STREAM MIX | LTM RECEIPTS ($)
A22: Streaming | B22: =Historical!D5 -> 780000 | C22: =IFERROR(B22/$B$8,0) -> 0.59541985
A23: Performance | B23: =Historical!D6 -> 210000 | C23: =IFERROR(B23/$B$8,0) -> 0.16030534
A24: Mechanical | B24: =Historical!D7 -> 110000 | C24: =IFERROR(B24/$B$8,0) -> 0.083969466
A25: Sync licensing | B25: =Historical!D8 -> 160000 | C25: =IFERROR(B25/$B$8,0) -> 0.1221374
A26: Other | B26: =Historical!D9 -> 50000 | C26: =IFERROR(B26/$B$8,0) -> 0.038167939
A27: TOTAL RECEIPTS | B27: =SUM(B22:B26) -> 1310000 | C27: =SUM(C22:C26) -> 1

Sheet Sources & Uses
A1: SOURCES & USES | FIVE-YEAR ACQUISITION
A3: VALUATION / PURCHASE PRICE
A5: LTM NLS/NPS proxy, attributable | B5: =Historical!D19*Assumptions!B43 -> 1106950
A6: Entry capitalization multiple | B6: =Assumptions!B44 -> 17
A7: Purchase enterprise value | B7: =B5*B6 -> 18818150
A8: Initial transaction fees | B8: =B7*Assumptions!B48 -> 282272.25
A9: TOTAL USES | B9: =SUM(B7:B8) -> 19100422
A12: TRANSACTION FINANCING
A14: Acquisition debt | B14: =B7*Assumptions!B46 -> 12231798
A15: Sponsor / investor equity | B15: =B9-B14 -> 6868624.8
A16: TOTAL SOURCES | B16: =SUM(B14:B15) -> 19100422
A18: Sources less uses check | B18: =B16-B9 -> 0
A21: KEY FINANCING ASSUMPTIONS
A22: Debt / purchase enterprise value | B22: =IFERROR(B14/B7,0) -> 0.65
A23: Equity / total uses | B23: =IFERROR(B15/B9,0) -> 0.35960591
A24: Debt borrowing rate | B24: =Assumptions!B47 -> 0.07
A25: Entry multiple | B25: =Assumptions!B44 -> 17
A28: Note: this is a catalog asset acquisition model, not a corporate equity value / net debt TEV bridge.
A29: Financing schedule models acquisition enterprise value, transaction fees, and debt/equity capital sources.

Sheet 5Y Underwriting
A1: FIVE-YEAR UNDERWRITING | NLS/NPS & INVESTOR RETURNS
A3: TRANSACTION SUMMARY
A5: LTM NLS/NPS proxy | B5: ='Sources & Uses'!B5 -> 1106950
A6: Entry multiple | B6: =Assumptions!B44 -> 17
A7: Exit multiple | B7: =Assumptions!B45 -> 17
A8: Purchase enterprise value | B8: ='Sources & Uses'!B7 -> 18818150
A9: Initial acquisition debt | B9: ='Sources & Uses'!B14 -> 12231798
A10: Initial equity contribution | B10: ='Sources & Uses'!B15 -> 6868624.8
A13: OPERATING CASH FLOW & DEBT ROLL-FORWARD
A15: Year / projection period | B15: 0 | C15: 1 | D15: 2 | E15: 3 | F15: 4 | G15: 5
A16: Projected NLS/NPS proxy (pre-tax) | B16: =B5 -> 1106950 | C16: =Forecast!B21*Assumptions!$B$43 -> 1128075 | D16: =Forecast!C21*Assumptions!$B$43 -> 1149832.5 | E16: =Forecast!D21*Assumptions!$B$43 -> 1172238 | F16: =Forecast!E21*Assumptions!$B$43 -> 1195307.5 | G16: =Forecast!F21*Assumptions!$B$43 -> 1219057.5
A17: Growth in proxy | C17: =IFERROR(C16/B16-1,0) -> 0.019083969 | D17: =IFERROR(D16/C16-1,0) -> 0.019287266 | E17: =IFERROR(E16/D16-1,0) -> 0.019485877 | F17: =IFERROR(F16/E16-1,0) -> 0.019679887 | G17: =IFERROR(G16/F16-1,0) -> 0.019869385
A18: After-tax unlevered operating CF | B18: =Historical!D17*Assumptions!$B$43 -> 830212.5 | C18: =Forecast!B17*Assumptions!$B$43 -> 846056.25 | D18: =Forecast!C17*Assumptions!$B$43 -> 862374.36 | E18: =Forecast!D17*Assumptions!$B$43 -> 879178.48 | F18: =Forecast!E17*Assumptions!$B$43 -> 896480.62 | G18: =Forecast!F17*Assumptions!$B$43 -> 914293.13
A20: Opening debt | C20: =$B$9 -> 12231798 | D20: =C23 -> 12231798 | E20: =D23 -> 12231798 | F20: =E23 -> 12231798 | G20: =F23 -> 12231798
A21: Interest expense (negative) | C21: =-C20*Assumptions!$B$47 -> -856225.83 | D21: =-D20*Assumptions!$B$47 -> -856225.83 | E21: =-E20*Assumptions!$B$47 -> -856225.83 | F21: =-F20*Assumptions!$B$47 -> -856225.83 | G21: =-G20*Assumptions!$B$47 -> -856225.83
A22: Principal repayment (negative) | C22: =-MIN(C20,$B$9*Assumptions!$B$50) -> 0 | D22: =-MIN(D20,$B$9*Assumptions!$B$50) -> 0 | E22: =-MIN(E20,$B$9*Assumptions!$B$50) -> 0 | F22: =-MIN(F20,$B$9*Assumptions!$B$50) -> 0 | G22: =-MIN(G20,$B$9*Assumptions!$B$50) -> 0
A23: Closing debt | C23: =SUM(C20,C22) -> 12231798 | D23: =SUM(D20,D22) -> 12231798 | E23: =SUM(E20,E22) -> 12231798 | F23: =SUM(F20,F22) -> 12231798 | G23: =SUM(G20,G22) -> 12231798
A24: Distributable equity cash flow | C24: =SUM(C18,C21:C22) -> -10169.575 | D24: =SUM(D18,D21:D22) -> 6148.5369 | E24: =SUM(E18,E21:E22) -> 22952.657 | F24: =SUM(F18,F21:F22) -> 40254.791 | G24: =SUM(G18,G21:G22) -> 58067.31
A26: Exit TEV from year-5 NLS/NPS | C26: =0 -> 0 | D26: =0 -> 0 | E26: =0 -> 0 | F26: =0 -> 0 | G26: =G16*$B$7 -> 20723978
A27: Exit fees (negative) | C27: =-C26*Assumptions!$B$49 -> 0 | D27: =-D26*Assumptions!$B$49 -> 0 | E27: =-E26*Assumptions!$B$49 -> 0 | F27: =-F26*Assumptions!$B$49 -> 0 | G27: =-G26*Assumptions!$B$49 -> -414479.55
A28: Debt repaid at exit (negative) | C28: =0 -> 0 | D28: =0 -> 0 | E28: =0 -> 0 | F28: =0 -> 0 | G28: =-G23 -> -12231798
A29: Net exit equity proceeds | C29: =SUM(C26:C28) -> 0 | D29: =SUM(D26:D28) -> 0 | E29: =SUM(E26:E28) -> 0 | F29: =SUM(F26:F28) -> 0 | G29: =SUM(G26:G28) -> 8077700.7
A31: Total levered investor cash flow | B31: =-B10 -> -6868624.8 | C31: =SUM(C24,C29) -> -10169.575 | D31: =SUM(D24,D29) -> 6148.5369 | E31: =SUM(E24,E29) -> 22952.657 | F31: =SUM(F24,F29) -> 40254.791 | G31: =SUM(G24,G29) -> 8135768
A32: Unlevered investor cash flow | B32: =-'Sources & Uses'!B9 -> -19100422 | C32: =SUM(C18,C26:C27) -> 846056.25 | D32: =SUM(D18,D26:D27) -> 862374.36 | E32: =SUM(E18,E26:E27) -> 879178.48 | F32: =SUM(F18,F26:F27) -> 896480.62 | G32: =SUM(G18,G26:G27) -> 21223791
A35: INVESTOR RETURNS & DECISION METRICS
A37: Levered 5Y IRR | B37: =IRR(B31:G31) -> 0.035999276
A38: Unlevered 5Y IRR | B38: =IRR(B32:G32) -> 0.057247364
A39: Equity MOIC | B39: =SUM(C31:G31)/-B31 -> 1.1930997
A40: Unlevered MOIC | B40: =SUM(C32:G32)/-B32 -> 1.2935777
A41: Year-5 run-rate equity cash yield | B41: =IFERROR(G24/$B$10,0) -> 0.0084539936
A42: Spread: levered IRR - interest rate | B42: =B37-Assumptions!B47 -> -0.034000724
A43: Parity exit vs entry multiple | B43: =IF(B6=B7,"PARITY","DIFFERENT") -> PARITY

Sheet 5Y Sensitivities
A1: FIVE-YEAR IRR | ENTRY / EXIT / FINANCING
A3: SCENARIO A | ENTRY TEV MULTIPLE × EXIT TEV MULTIPLE
A5: Entry multiple ↓ / exit multiple →
C6: =Assumptions!$B$45+-2 -> 15 | D6: =Assumptions!$B$45+-1 -> 16 | E6: =Assumptions!$B$45+0 -> 17 | F6: =Assumptions!$B$45+1 -> 18 | G6: =Assumptions!$B$45+2 -> 19
B7: =Assumptions!$B$44+-2 -> 15 | C7: =M14 -> 0.051939443 | D7: =M15 -> 0.083238737 | E7: =M16 -> 0.11124331 | F7: =M17 -> 0.13664516 | G7: =M18 -> 0.15993343
B8: =Assumptions!$B$44+-1 -> 16 | C8: =M19 -> 0.0096466699 | D8: =M20 -> 0.043469526 | E8: =M21 -> 0.073370843 | F8: =M22 -> 0.10024674 | G8: =M23 -> 0.12471017
B9: =Assumptions!$B$44+0 -> 17 | C9: =M24 -> -0.033140246 | D9: =M25 -> 0.0038113902 | E9: =M26 -> 0.035999276 | F9: =M27 -> 0.064616279 | G9: =M28 -> 0.090446677
B10: =Assumptions!$B$44+1 -> 18 | C10: =M29 -> -0.077254315 | D10: =M30 -> -0.036327475 | E10: =M31 -> -0.0013364765 | F10: =M32 -> 0.029361601 | G10: =M33 -> 0.056795625
B11: =Assumptions!$B$44+2 -> 19 | C11: =M34 -> -0.1237815 | D11: =M35 -> -0.077637014 | E11: =M36 -> -0.039134542 | F11: =M37 -> -0.0059111486 | G11: =M38 -> 0.023424676
A14: Scenario A 1-1 | B14: =$B7 -> 15 | C14: =C$6 -> 15 | D14: ='Rights Basis'!$B$11*B14 -> 16604250 | E14: =D14*Assumptions!$B$46 -> 10792762 | F14: =D14*(1+Assumptions!$B$48)-E14 -> 6060551.2 | G14: =-F14 -> -6060551.2 | H14: ='5Y Underwriting'!C18-MAX(0,E14*(1-(1-1)*Assumptions!$B$50))*Assumptions!$B$47-MIN(MAX(0,E14*(1-(1-1)*Assumptions!$B$50)),E14*Assumptions!$B$50) -> 90562.875 | I14: ='5Y Underwriting'!D18-MAX(0,E14*(1-(2-1)*Assumptions!$B$50))*Assumptions!$B$47-MIN(MAX(0,E14*(1-(2-1)*Assumptions!$B$50)),E14*Assumptions!$B$50) -> 106880.99 | J14: ='5Y Underwriting'!E18-MAX(0,E14*(1-(3-1)*Assumptions!$B$50))*Assumptions!$B$47-MIN(MAX(0,E14*(1-(3-1)*Assumptions!$B$50)),E14*Assumptions!$B$50) -> 123685.11 | K14: ='5Y Underwriting'!F18-MAX(0,E14*(1-(4-1)*Assumptions!$B$50))*Assumptions!$B$47-MIN(MAX(0,E14*(1-(4-1)*Assumptions!$B$50)),E14*Assumptions!$B$50) -> 140987.24 | L14: ='5Y Underwriting'!G18-MAX(0,E14*(1-(5-1)*Assumptions!$B$50))*Assumptions!$B$47-MIN(MAX(0,E14*(1-(5-1)*Assumptions!$B$50)),E14*Assumptions!$B$50)+'5Y Underwriting'!$G$16*C14*(1-Assumptions!$B$49)-MAX(0,E14*(1-5*Assumptions!$B$50)) -> 7286182.7 | M14: =IFERROR(IRR(G14:L14),0) -> 0.051939443
A15: Scenario A 1-2 | B15: =$B7 -> 15 | C15: =D$6 -> 16 | D15: ='Rights Basis'!$B$11*B15 -> 16604250 | E15: =D15*Assumptions!$B$46 -> 10792762 | F15: =D15*(1+Assumptions!$B$48)-E15 -> 6060551.2 | G15: =-F15 -> -6060551.2 | H15: ='5Y Underwriting'!C18-MAX(0,E15*(1-(1-1)*Assumptions!$B$50))*Assumptions!$B$47-MIN(MAX(0,E15*(1-(1-1)*Assumptions!$B$50)),E15*Assumptions!$B$50) -> 90562.875 | I15: ='5Y Underwriting'!D18-MAX(0,E15*(1-(2-1)*Assumptions!$B$50))*Assumptions!$B$47-MIN(MAX(0,E15*(1-(2-1)*Assumptions!$B$50)),E15*Assumptions!$B$50) -> 106880.99 | J15: ='5Y Underwriting'!E18-MAX(0,E15*(1-(3-1)*Assumptions!$B$50))*Assumptions!$B$47-MIN(MAX(0,E15*(1-(3-1)*Assumptions!$B$50)),E15*Assumptions!$B$50) -> 123685.11 | K15: ='5Y Underwriting'!F18-MAX(0,E15*(1-(4-1)*Assumptions!$B$50))*Assumptions!$B$47-MIN(MAX(0,E15*(1-(4-1)*Assumptions!$B$50)),E15*Assumptions!$B$50) -> 140987.24 | L15: ='5Y Underwriting'!G18-MAX(0,E15*(1-(5-1)*Assumptions!$B$50))*Assumptions!$B$47-MIN(MAX(0,E15*(1-(5-1)*Assumptions!$B$50)),E15*Assumptions!$B$50)+'5Y Underwriting'!$G$16*C15*(1-Assumptions!$B$49)-MAX(0,E15*(1-5*Assumptions!$B$50)) -> 8480859.1 | M15: =IFERROR(IRR(G15:L15),0) -> 0.083238737
A16: Scenario A 1-3 | B16: =$B7 -> 15 | C16: =E$6 -> 17 | D16: ='Rights Basis'!$B$11*B16 -> 16604250 | E16: =D16*Assumptions!$B$46 -> 10792762 | F16: =D16*(1+Assumptions!$B$48)-E16 -> 6060551.2 | G16: =-F16 -> -6060551.2 | H16: ='5Y Underwriting'!C18-MAX(0,E16*(1-(1-1)*Assumptions!$B$50))*Assumptions!$B$47-MIN(MAX(0,E16*(1-(1-1)*Assumptions!$B$50)),E16*Assumptions!$B$50) -> 90562.875 | I16: ='5Y Underwriting'!D18-MAX(0,E16*(1-(2-1)*Assumptions!$B$50))*Assumptions!$B$47-MIN(MAX(0,E16*(1-(2-1)*Assumptions!$B$50)),E16*Assumptions!$B$50) -> 106880.99 | J16: ='5Y Underwriting'!E18-MAX(0,E16*(1-(3-1)*Assumptions!$B$50))*Assumptions!$B$47-MIN(MAX(0,E16*(1-(3-1)*Assumptions!$B$50)),E16*Assumptions!$B$50) -> 123685.11 | K16: ='5Y Underwriting'!F18-MAX(0,E16*(1-(4-1)*Assumptions!$B$50))*Assumptions!$B$47-MIN(MAX(0,E16*(1-(4-1)*Assumptions!$B$50)),E16*Assumptions!$B$50) -> 140987.24 | L16: ='5Y Underwriting'!G18-MAX(0,E16*(1-(5-1)*Assumptions!$B$50))*Assumptions!$B$47-MIN(MAX(0,E16*(1-(5-1)*Assumptions!$B$50)),E16*Assumptions!$B$50)+'5Y Underwriting'!$G$16*C16*(1-Assumptions!$B$49)-MAX(0,E16*(1-5*Assumptions!$B$50)) -> 9675535.4 | M16: =IFERROR(IRR(G16:L16),0) -> 0.11124331
A17: Scenario A 1-4 | B17: =$B7 -> 15 | C17: =F$6 -> 18 | D17: ='Rights Basis'!$B$11*B17 -> 16604250 | E17: =D17*Assumptions!$B$46 -> 10792762 | F17: =D17*(1+Assumptions!$B$48)-E17 -> 6060551.2 | G17: =-F17 -> -6060551.2 | H17: ='5Y Underwriting'!C18-MAX(0,E17*(1-(1-1)*Assumptions!$B$50))*Assumptions!$B$47-MIN(MAX(0,E17*(1-(1-1)*Assumptions!$B$50)),E17*Assumptions!$B$50) -> 90562.875 | I17: ='5Y Underwriting'!D18-MAX(0,E17*(1-(2-1)*Assumptions!$B$50))*Assumptions!$B$47-MIN(MAX(0,E17*(1-(2-1)*Assumptions!$B$50)),E17*Assumptions!$B$50) -> 106880.99 | J17: ='5Y Underwriting'!E18-MAX(0,E17*(1-(3-1)*Assumptions!$B$50))*Assumptions!$B$47-MIN(MAX(0,E17*(1-(3-1)*Assumptions!$B$50)),E17*Assumptions!$B$50) -> 123685.11 | K17: ='5Y Underwriting'!F18-MAX(0,E17*(1-(4-1)*Assumptions!$B$50))*Assumptions!$B$47-MIN(MAX(0,E17*(1-(4-1)*Assumptions!$B$50)),E17*Assumptions!$B$50) -> 140987.24 | L17: ='5Y Underwriting'!G18-MAX(0,E17*(1-(5-1)*Assumptions!$B$50))*Assumptions!$B$47-MIN(MAX(0,E17*(1-(5-1)*Assumptions!$B$50)),E17*Assumptions!$B$50)+'5Y Underwriting'!$G$16*C17*(1-Assumptions!$B$49)-MAX(0,E17*(1-5*Assumptions!$B$50)) -> 10870212 | M17: =IFERROR(IRR(G17:L17),0) -> 0.13664516
A18: Scenario A 1-5 | B18: =$B7 -> 15 | C18: =G$6 -> 19 | D18: ='Rights Basis'!$B$11*B18 -> 16604250 | E18: =D18*Assumptions!$B$46 -> 10792762 | F18: =D18*(1+Assumptions!$B$48)-E18 -> 6060551.2 | G18: =-F18 -> -6060551.2 | H18: ='5Y Underwriting'!C18-MAX(0,E18*(1-(1-1)*Assumptions!$B$50))*Assumptions!$B$47-MIN(MAX(0,E18*(1-(1-1)*Assumptions!$B$50)),E18*Assumptions!$B$50) -> 90562.875 | I18: ='5Y Underwriting'!D18-MAX(0,E18*(1-(2-1)*Assumptions!$B$50))*Assumptions!$B$47-MIN(MAX(0,E18*(1-(2-1)*Assumptions!$B$50)),E18*Assumptions!$B$50) -> 106880.99 | J18: ='5Y Underwriting'!E18-MAX(0,E18*(1-(3-1)*Assumptions!$B$50))*Assumptions!$B$47-MIN(MAX(0,E18*(1-(3-1)*Assumptions!$B$50)),E18*Assumptions!$B$50) -> 123685.11 | K18: ='5Y Underwriting'!F18-MAX(0,E18*(1-(4-1)*Assumptions!$B$50))*Assumptions!$B$47-MIN(MAX(0,E18*(1-(4-1)*Assumptions!$B$50)),E18*Assumptions!$B$50) -> 140987.24 | L18: ='5Y Underwriting'!G18-MAX(0,E18*(1-(5-1)*Assumptions!$B$50))*Assumptions!$B$47-MIN(MAX(0,E18*(1-(5-1)*Assumptions!$B$50)),E18*Assumptions!$B$50)+'5Y Underwriting'!$G$16*C18*(1-Assumptions!$B$49)-MAX(0,E18*(1-5*Assumptions!$B$50)) -> 12064888 | M18: =IFERROR(IRR(G18:L18),0) -> 0.15993343
A19: Scenario A 2-1 | B19: =$B8 -> 16 | C19: =C$6 -> 15 | D19: ='Rights Basis'!$B$11*B19 -> 17711200 | E19: =D19*Assumptions!$B$46 -> 11512280 | F19: =D19*(1+Assumptions!$B$48)-E19 -> 6464588 | G19: =-F19 -> -6464588 | H19: ='5Y Underwriting'!C18-MAX(0,E19*(1-(1-1)*Assumptions!$B$50))*Assumptions!$B$47-MIN(MAX(0,E19*(1-(1-1)*Assumptions!$B$50)),E19*Assumptions!$B$50) -> 40196.65 | I19: ='5Y Underwriting'!D18-MAX(0,E19*(1-(2-1)*Assumptions!$B$50))*Assumptions!$B$47-MIN(MAX(0,E19*(1-(2-1)*Assumptions!$B$50)),E19*Assumptions!$B$50) -> 56514.762 | J19: ='5Y Underwriting'!E18-MAX(0,E19*(1-(3-1)*Assumptions!$B$50))*Assumptions!$B$47-MIN(MAX(0,E19*(1-(3-1)*Assumptions!$B$50)),E19*Assumptions!$B$50) -> 73318.882 | K19: ='5Y Underwriting'!F18-MAX(0,E19*(1-(4-1)*Assumptions!$B$50))*Assumptions!$B$47-MIN(MAX(0,E19*(1-(4-1)*Assumptions!$B$50)),E19*Assumptions!$B$50) -> 90621.016 | L19: ='5Y Underwriting'!G18-MAX(0,E19*(1-(5-1)*Assumptions!$B$50))*Assumptions!$B$47-MIN(MAX(0,E19*(1-(5-1)*Assumptions!$B$50)),E19*Assumptions!$B$50)+'5Y Underwriting'!$G$16*C19*(1-Assumptions!$B$49)-MAX(0,E19*(1-5*Assumptions!$B$50)) -> 6516299 | M19: =IFERROR(IRR(G19:L19),0) -> 0.0096466699
A20: Scenario A 2-2 | B20: =$B8 -> 16 | C20: =D$6 -> 16 | D20: ='Rights Basis'!$B$11*B20 -> 17711200 | E20: =D20*Assumptions!$B$46 -> 11512280 | F20: =D20*(1+Assumptions!$B$48)-E20 -> 6464588 | G20: =-F20 -> -6464588 | H20: ='5Y Underwriting'!C18-MAX(0,E20*(1-(1-1)*Assumptions!$B$50))*Assumptions!$B$47-MIN(MAX(0,E20*(1-(1-1)*Assumptions!$B$50)),E20*Assumptions!$B$50) -> 40196.65 | I20: ='5Y Underwriting'!D18-MAX(0,E20*(1-(2-1)*Assumptions!$B$50))*Assumptions!$B$47-MIN(MAX(0,E20*(1-(2-1)*Assumptions!$B$50)),E20*Assumptions!$B$50) -> 56514.762 | J20: ='5Y Underwriting'!E18-MAX(0,E20*(1-(3-1)*Assumptions!$B$50))*Assumptions!$B$47-MIN(MAX(0,E20*(1-(3-1)*Assumptions!$B$50)),E20*Assumptions!$B$50) -> 73318.882 | K20: ='5Y Underwriting'!F18-MAX(0,E20*(1-(4-1)*Assumptions!$B$50))*Assumptions!$B$47-MIN(MAX(0,E20*(1-(4-1)*Assumptions!$B$50)),E20*Assumptions!$B$50) -> 90621.016 | L20: ='5Y Underwriting'!G18-MAX(0,E20*(1-(5-1)*Assumptions!$B$50))*Assumptions!$B$47-MIN(MAX(0,E20*(1-(5-1)*Assumptions!$B$50)),E20*Assumptions!$B$50)+'5Y Underwriting'!$G$16*C20*(1-Assumptions!$B$49)-MAX(0,E20*(1-5*Assumptions!$B$50)) -> 7710975.3 | M20: =IFERROR(IRR(G20:L20),0) -> 0.043469526
A21: Scenario A 2-3 | B21: =$B8 -> 16 | C21: =E$6 -> 17 | D21: ='Rights Basis'!$B$11*B21 -> 17711200 | E21: =D21*Assumptions!$B$46 -> 11512280 | F21: =D21*(1+Assumptions!$B$48)-E21 -> 6464588 | G21: =-F21 -> -6464588 | H21: ='5Y Underwriting'!C18-MAX(0,E21*(1-(1-1)*Assumptions!$B$50))*Assumptions!$B$47-MIN(MAX(0,E21*(1-(1-1)*Assumptions!$B$50)),E21*Assumptions!$B$50) -> 40196.65 | I21: ='5Y Underwriting'!D18-MAX(0,E21*(1-(2-1)*Assumptions!$B$50))*Assumptions!$B$47-MIN(MAX(0,E21*(1-(2-1)*Assumptions!$B$50)),E21*Assumptions!$B$50) -> 56514.762 | J21: ='5Y Underwriting'!E18-MAX(0,E21*(1-(3-1)*Assumptions!$B$50))*Assumptions!$B$47-MIN(MAX(0,E21*(1-(3-1)*Assumptions!$B$50)),E21*Assumptions!$B$50) -> 73318.882 | K21: ='5Y Underwriting'!F18-MAX(0,E21*(1-(4-1)*Assumptions!$B$50))*Assumptions!$B$47-MIN(MAX(0,E21*(1-(4-1)*Assumptions!$B$50)),E21*Assumptions!$B$50) -> 90621.016 | L21: ='5Y Underwriting'!G18-MAX(0,E21*(1-(5-1)*Assumptions!$B$50))*Assumptions!$B$47-MIN(MAX(0,E21*(1-(5-1)*Assumptions!$B$50)),E21*Assumptions!$B$50)+'5Y Underwriting'!$G$16*C21*(1-Assumptions!$B$49)-MAX(0,E21*(1-5*Assumptions!$B$50)) -> 8905651.7 | M21: =IFERROR(IRR(G21:L21),0) -> 0.073370843
A22: Scenario A 2-4 | B22: =$B8 -> 16 | C22: =F$6 -> 18 | D22: ='Rights Basis'!$B$11*B22 -> 17711200 | E22: =D22*Assumptions!$B$46 -> 11512280 | F22: =D22*(1+Assumptions!$B$48)-E22 -> 6464588 | G22: =-F22 -> -6464588 | H22: ='5Y Underwriting'!C18-MAX(0,E22*(1-(1-1)*Assumptions!$B$50))*Assumptions!$B$47-MIN(MAX(0,E22*(1-(1-1)*Assumptions!$B$50)),E22*Assumptions!$B$50) -> 40196.65 | I22: ='5Y Underwriting'!D18-MAX(0,E22*(1-(2-1)*Assumptions!$B$50))*Assumptions!$B$47-MIN(MAX(0,E22*(1-(2-1)*Assumptions!$B$50)),E22*Assumptions!$B$50) -> 56514.762 | J22: ='5Y Underwriting'!E18-MAX(0,E22*(1-(3-1)*Assumptions!$B$50))*Assumptions!$B$47-MIN(MAX(0,E22*(1-(3-1)*Assumptions!$B$50)),E22*Assumptions!$B$50) -> 73318.882 | K22: ='5Y Underwriting'!F18-MAX(0,E22*(1-(4-1)*Assumptions!$B$50))*Assumptions!$B$47-MIN(MAX(0,E22*(1-(4-1)*Assumptions!$B$50)),E22*Assumptions!$B$50) -> 90621.016 | L22: ='5Y Underwriting'!G18-MAX(0,E22*(1-(5-1)*Assumptions!$B$50))*Assumptions!$B$47-MIN(MAX(0,E22*(1-(5-1)*Assumptions!$B$50)),E22*Assumptions!$B$50)+'5Y Underwriting'!$G$16*C22*(1-Assumptions!$B$49)-MAX(0,E22*(1-5*Assumptions!$B$50)) -> 10100328 | M22: =IFERROR(IRR(G22:L22),0) -> 0.10024674
A23: Scenario A 2-5 | B23: =$B8 -> 16 | C23: =G$6 -> 19 | D23: ='Rights Basis'!$B$11*B23 -> 17711200 | E23: =D23*Assumptions!$B$46 -> 11512280 | F23: =D23*(1+Assumptions!$B$48)-E23 -> 6464588 | G23: =-F23 -> -6464588 | H23: ='5Y Underwriting'!C18-MAX(0,E23*(1-(1-1)*Assumptions!$B$50))*Assumptions!$B$47-MIN(MAX(0,E23*(1-(1-1)*Assumptions!$B$50)),E23*Assumptions!$B$50) -> 40196.65 | I23: ='5Y Underwriting'!D18-MAX(0,E23*(1-(2-1)*Assumptions!$B$50))*Assumptions!$B$47-MIN(MAX(0,E23*(1-(2-1)*Assumptions!$B$50)),E23*Assumptions!$B$50) -> 56514.762 | J23: ='5Y Underwriting'!E18-MAX(0,E23*(1-(3-1)*Assumptions!$B$50))*Assumptions!$B$47-MIN(MAX(0,E23*(1-(3-1)*Assumptions!$B$50)),E23*Assumptions!$B$50) -> 73318.882 | K23: ='5Y Underwriting'!F18-MAX(0,E23*(1-(4-1)*Assumptions!$B$50))*Assumptions!$B$47-MIN(MAX(0,E23*(1-(4-1)*Assumptions!$B$50)),E23*Assumptions!$B$50) -> 90621.016 | L23: ='5Y Underwriting'!G18-MAX(0,E23*(1-(5-1)*Assumptions!$B$50))*Assumptions!$B$47-MIN(MAX(0,E23*(1-(5-1)*Assumptions!$B$50)),E23*Assumptions!$B$50)+'5Y Underwriting'!$G$16*C23*(1-Assumptions!$B$49)-MAX(0,E23*(1-5*Assumptions!$B$50)) -> 11295004 | M23: =IFERROR(IRR(G23:L23),0) -> 0.12471017
A24: Scenario A 3-1 | B24: =$B9 -> 17 | C24: =C$6 -> 15 | D24: ='Rights Basis'!$B$11*B24 -> 18818150 | E24: =D24*Assumptions!$B$46 -> 12231798 | F24: =D24*(1+Assumptions!$B$48)-E24 -> 6868624.8 | G24: =-F24 -> -6868624.8 | H24: ='5Y Underwriting'!C18-MAX(0,E24*(1-(1-1)*Assumptions!$B$50))*Assumptions!$B$47-MIN(MAX(0,E24*(1-(1-1)*Assumptions!$B$50)),E24*Assumptions!$B$50) -> -10169.575 | I24: ='5Y Underwriting'!D18-MAX(0,E24*(1-(2-1)*Assumptions!$B$50))*Assumptions!$B$47-MIN(MAX(0,E24*(1-(2-1)*Assumptions!$B$50)),E24*Assumptions!$B$50) -> 6148.5369 | J24: ='5Y Underwriting'!E18-MAX(0,E24*(1-(3-1)*Assumptions!$B$50))*Assumptions!$B$47-MIN(MAX(0,E24*(1-(3-1)*Assumptions!$B$50)),E24*Assumptions!$B$50) -> 22952.657 | K24: ='5Y Underwriting'!F18-MAX(0,E24*(1-(4-1)*Assumptions!$B$50))*Assumptions!$B$47-MIN(MAX(0,E24*(1-(4-1)*Assumptions!$B$50)),E24*Assumptions!$B$50) -> 40254.791 | L24: ='5Y Underwriting'!G18-MAX(0,E24*(1-(5-1)*Assumptions!$B$50))*Assumptions!$B$47-MIN(MAX(0,E24*(1-(5-1)*Assumptions!$B$50)),E24*Assumptions!$B$50)+'5Y Underwriting'!$G$16*C24*(1-Assumptions!$B$49)-MAX(0,E24*(1-5*Assumptions!$B$50)) -> 5746415.3 | M24: =IFERROR(IRR(G24:L24),0) -> -0.033140246
A25: Scenario A 3-2 | B25: =$B9 -> 17 | C25: =D$6 -> 16 | D25: ='Rights Basis'!$B$11*B25 -> 18818150 | E25: =D25*Assumptions!$B$46 -> 12231798 | F25: =D25*(1+Assumptions!$B$48)-E25 -> 6868624.8 | G25: =-F25 -> -6868624.8 | H25: ='5Y Underwriting'!C18-MAX(0,E25*(1-(1-1)*Assumptions!$B$50))*Assumptions!$B$47-MIN(MAX(0,E25*(1-(1-1)*Assumptions!$B$50)),E25*Assumptions!$B$50) -> -10169.575 | I25: ='5Y Underwriting'!D18-MAX(0,E25*(1-(2-1)*Assumptions!$B$50))*Assumptions!$B$47-MIN(MAX(0,E25*(1-(2-1)*Assumptions!$B$50)),E25*Assumptions!$B$50) -> 6148.5369 | J25: ='5Y Underwriting'!E18-MAX(0,E25*(1-(3-1)*Assumptions!$B$50))*Assumptions!$B$47-MIN(MAX(0,E25*(1-(3-1)*Assumptions!$B$50)),E25*Assumptions!$B$50) -> 22952.657 | K25: ='5Y Underwriting'!F18-MAX(0,E25*(1-(4-1)*Assumptions!$B$50))*Assumptions!$B$47-MIN(MAX(0,E25*(1-(4-1)*Assumptions!$B$50)),E25*Assumptions!$B$50) -> 40254.791 | L25: ='5Y Underwriting'!G18-MAX(0,E25*(1-(5-1)*Assumptions!$B$50))*Assumptions!$B$47-MIN(MAX(0,E25*(1-(5-1)*Assumptions!$B$50)),E25*Assumptions!$B$50)+'5Y Underwriting'!$G$16*C25*(1-Assumptions!$B$49)-MAX(0,E25*(1-5*Assumptions!$B$50)) -> 6941091.6 | M25: =IFERROR(IRR(G25:L25),0) -> 0.0038113902
A26: Scenario A 3-3 | B26: =$B9 -> 17 | C26: =E$6 -> 17 | D26: ='Rights Basis'!$B$11*B26 -> 18818150 | E26: =D26*Assumptions!$B$46 -> 12231798 | F26: =D26*(1+Assumptions!$B$48)-E26 -> 6868624.8 | G26: =-F26 -> -6868624.8 | H26: ='5Y Underwriting'!C18-MAX(0,E26*(1-(1-1)*Assumptions!$B$50))*Assumptions!$B$47-MIN(MAX(0,E26*(1-(1-1)*Assumptions!$B$50)),E26*Assumptions!$B$50) -> -10169.575 | I26: ='5Y Underwriting'!D18-MAX(0,E26*(1-(2-1)*Assumptions!$B$50))*Assumptions!$B$47-MIN(MAX(0,E26*(1-(2-1)*Assumptions!$B$50)),E26*Assumptions!$B$50) -> 6148.5369 | J26: ='5Y Underwriting'!E18-MAX(0,E26*(1-(3-1)*Assumptions!$B$50))*Assumptions!$B$47-MIN(MAX(0,E26*(1-(3-1)*Assumptions!$B$50)),E26*Assumptions!$B$50) -> 22952.657 | K26: ='5Y Underwriting'!F18-MAX(0,E26*(1-(4-1)*Assumptions!$B$50))*Assumptions!$B$47-MIN(MAX(0,E26*(1-(4-1)*Assumptions!$B$50)),E26*Assumptions!$B$50) -> 40254.791 | L26: ='5Y Underwriting'!G18-MAX(0,E26*(1-(5-1)*Assumptions!$B$50))*Assumptions!$B$47-MIN(MAX(0,E26*(1-(5-1)*Assumptions!$B$50)),E26*Assumptions!$B$50)+'5Y Underwriting'!$G$16*C26*(1-Assumptions!$B$49)-MAX(0,E26*(1-5*Assumptions!$B$50)) -> 8135768 | M26: =IFERROR(IRR(G26:L26),0) -> 0.035999276
A27: Scenario A 3-4 | B27: =$B9 -> 17 | C27: =F$6 -> 18 | D27: ='Rights Basis'!$B$11*B27 -> 18818150 | E27: =D27*Assumptions!$B$46 -> 12231798 | F27: =D27*(1+Assumptions!$B$48)-E27 -> 6868624.8 | G27: =-F27 -> -6868624.8 | H27: ='5Y Underwriting'!C18-MAX(0,E27*(1-(1-1)*Assumptions!$B$50))*Assumptions!$B$47-MIN(MAX(0,E27*(1-(1-1)*Assumptions!$B$50)),E27*Assumptions!$B$50) -> -10169.575 | I27: ='5Y Underwriting'!D18-MAX(0,E27*(1-(2-1)*Assumptions!$B$50))*Assumptions!$B$47-MIN(MAX(0,E27*(1-(2-1)*Assumptions!$B$50)),E27*Assumptions!$B$50) -> 6148.5369 | J27: ='5Y Underwriting'!E18-MAX(0,E27*(1-(3-1)*Assumptions!$B$50))*Assumptions!$B$47-MIN(MAX(0,E27*(1-(3-1)*Assumptions!$B$50)),E27*Assumptions!$B$50) -> 22952.657 | K27: ='5Y Underwriting'!F18-MAX(0,E27*(1-(4-1)*Assumptions!$B$50))*Assumptions!$B$47-MIN(MAX(0,E27*(1-(4-1)*Assumptions!$B$50)),E27*Assumptions!$B$50) -> 40254.791 | L27: ='5Y Underwriting'!G18-MAX(0,E27*(1-(5-1)*Assumptions!$B$50))*Assumptions!$B$47-MIN(MAX(0,E27*(1-(5-1)*Assumptions!$B$50)),E27*Assumptions!$B$50)+'5Y Underwriting'!$G$16*C27*(1-Assumptions!$B$49)-MAX(0,E27*(1-5*Assumptions!$B$50)) -> 9330444.3 | M27: =IFERROR(IRR(G27:L27),0) -> 0.064616279
A28: Scenario A 3-5 | B28: =$B9 -> 17 | C28: =G$6 -> 19 | D28: ='Rights Basis'!$B$11*B28 -> 18818150 | E28: =D28*Assumptions!$B$46 -> 12231798 | F28: =D28*(1+Assumptions!$B$48)-E28 -> 6868624.8 | G28: =-F28 -> -6868624.8 | H28: ='5Y Underwriting'!C18-MAX(0,E28*(1-(1-1)*Assumptions!$B$50))*Assumptions!$B$47-MIN(MAX(0,E28*(1-(1-1)*Assumptions!$B$50)),E28*Assumptions!$B$50) -> -10169.575 | I28: ='5Y Underwriting'!D18-MAX(0,E28*(1-(2-1)*Assumptions!$B$50))*Assumptions!$B$47-MIN(MAX(0,E28*(1-(2-1)*Assumptions!$B$50)),E28*Assumptions!$B$50) -> 6148.5369 | J28: ='5Y Underwriting'!E18-MAX(0,E28*(1-(3-1)*Assumptions!$B$50))*Assumptions!$B$47-MIN(MAX(0,E28*(1-(3-1)*Assumptions!$B$50)),E28*Assumptions!$B$50) -> 22952.657 | K28: ='5Y Underwriting'!F18-MAX(0,E28*(1-(4-1)*Assumptions!$B$50))*Assumptions!$B$47-MIN(MAX(0,E28*(1-(4-1)*Assumptions!$B$50)),E28*Assumptions!$B$50) -> 40254.791 | L28: ='5Y Underwriting'!G18-MAX(0,E28*(1-(5-1)*Assumptions!$B$50))*Assumptions!$B$47-MIN(MAX(0,E28*(1-(5-1)*Assumptions!$B$50)),E28*Assumptions!$B$50)+'5Y Underwriting'!$G$16*C28*(1-Assumptions!$B$49)-MAX(0,E28*(1-5*Assumptions!$B$50)) -> 10525121 | M28: =IFERROR(IRR(G28:L28),0) -> 0.090446677
A29: Scenario A 4-1 | B29: =$B10 -> 18 | C29: =C$6 -> 15 | D29: ='Rights Basis'!$B$11*B29 -> 19925100 | E29: =D29*Assumptions!$B$46 -> 12951315 | F29: =D29*(1+Assumptions!$B$48)-E29 -> 7272661.5 | G29: =-F29 -> -7272661.5 | H29: ='5Y Underwriting'!C18-MAX(0,E29*(1-(1-1)*Assumptions!$B$50))*Assumptions!$B$47-MIN(MAX(0,E29*(1-(1-1)*Assumptions!$B$50)),E29*Assumptions!$B$50) -> -60535.8 | I29: ='5Y Underwriting'!D18-MAX(0,E29*(1-(2-1)*Assumptions!$B$50))*Assumptions!$B$47-MIN(MAX(0,E29*(1-(2-1)*Assumptions!$B$50)),E29*Assumptions!$B$50) -> -44217.688 | J29: ='5Y Underwriting'!E18-MAX(0,E29*(1-(3-1)*Assumptions!$B$50))*Assumptions!$B$47-MIN(MAX(0,E29*(1-(3-1)*Assumptions!$B$50)),E29*Assumptions!$B$50) -> -27413.568 | K29: ='5Y Underwriting'!F18-MAX(0,E29*(1-(4-1)*Assumptions!$B$50))*Assumptions!$B$47-MIN(MAX(0,E29*(1-(4-1)*Assumptions!$B$50)),E29*Assumptions!$B$50) -> -10111.434 | L29: ='5Y Underwriting'!G18-MAX(0,E29*(1-(5-1)*Assumptions!$B$50))*Assumptions!$B$47-MIN(MAX(0,E29*(1-(5-1)*Assumptions!$B$50)),E29*Assumptions!$B$50)+'5Y Underwriting'!$G$16*C29*(1-Assumptions!$B$49)-MAX(0,E29*(1-5*Assumptions!$B$50)) -> 4976531.5 | M29: =IFERROR(IRR(G29:L29),0) -> -0.077254315
A30: Scenario A 4-2 | B30: =$B10 -> 18 | C30: =D$6 -> 16 | D30: ='Rights Basis'!$B$11*B30 -> 19925100 | E30: =D30*Assumptions!$B$46 -> 12951315 | F30: =D30*(1+Assumptions!$B$48)-E30 -> 7272661.5 | G30: =-F30 -> -7272661.5 | H30: ='5Y Underwriting'!C18-MAX(0,E30*(1-(1-1)*Assumptions!$B$50))*Assumptions!$B$47-MIN(MAX(0,E30*(1-(1-1)*Assumptions!$B$50)),E30*Assumptions!$B$50) -> -60535.8 | I30: ='5Y Underwriting'!D18-MAX(0,E30*(1-(2-1)*Assumptions!$B$50))*Assumptions!$B$47-MIN(MAX(0,E30*(1-(2-1)*Assumptions!$B$50)),E30*Assumptions!$B$50) -> -44217.688 | J30: ='5Y Underwriting'!E18-MAX(0,E30*(1-(3-1)*Assumptions!$B$50))*Assumptions!$B$47-MIN(MAX(0,E30*(1-(3-1)*Assumptions!$B$50)),E30*Assumptions!$B$50) -> -27413.568 | K30: ='5Y Underwriting'!F18-MAX(0,E30*(1-(4-1)*Assumptions!$B$50))*Assumptions!$B$47-MIN(MAX(0,E30*(1-(4-1)*Assumptions!$B$50)),E30*Assumptions!$B$50) -> -10111.434 | L30: ='5Y Underwriting'!G18-MAX(0,E30*(1-(5-1)*Assumptions!$B$50))*Assumptions!$B$47-MIN(MAX(0,E30*(1-(5-1)*Assumptions!$B$50)),E30*Assumptions!$B$50)+'5Y Underwriting'!$G$16*C30*(1-Assumptions!$B$49)-MAX(0,E30*(1-5*Assumptions!$B$50)) -> 6171207.9 | M30: =IFERROR(IRR(G30:L30),0) -> -0.036327475
A31: Scenario A 4-3 | B31: =$B10 -> 18 | C31: =E$6 -> 17 | D31: ='Rights Basis'!$B$11*B31 -> 19925100 | E31: =D31*Assumptions!$B$46 -> 12951315 | F31: =D31*(1+Assumptions!$B$48)-E31 -> 7272661.5 | G31: =-F31 -> -7272661.5 | H31: ='5Y Underwriting'!C18-MAX(0,E31*(1-(1-1)*Assumptions!$B$50))*Assumptions!$B$47-MIN(MAX(0,E31*(1-(1-1)*Assumptions!$B$50)),E31*Assumptions!$B$50) -> -60535.8 | I31: ='5Y Underwriting'!D18-MAX(0,E31*(1-(2-1)*Assumptions!$B$50))*Assumptions!$B$47-MIN(MAX(0,E31*(1-(2-1)*Assumptions!$B$50)),E31*Assumptions!$B$50) -> -44217.688 | J31: ='5Y Underwriting'!E18-MAX(0,E31*(1-(3-1)*Assumptions!$B$50))*Assumptions!$B$47-MIN(MAX(0,E31*(1-(3-1)*Assumptions!$B$50)),E31*Assumptions!$B$50) -> -27413.568 | K31: ='5Y Underwriting'!F18-MAX(0,E31*(1-(4-1)*Assumptions!$B$50))*Assumptions!$B$47-MIN(MAX(0,E31*(1-(4-1)*Assumptions!$B$50)),E31*Assumptions!$B$50) -> -10111.434 | L31: ='5Y Underwriting'!G18-MAX(0,E31*(1-(5-1)*Assumptions!$B$50))*Assumptions!$B$47-MIN(MAX(0,E31*(1-(5-1)*Assumptions!$B$50)),E31*Assumptions!$B$50)+'5Y Underwriting'!$G$16*C31*(1-Assumptions!$B$49)-MAX(0,E31*(1-5*Assumptions!$B$50)) -> 7365884.3 | M31: =IFERROR(IRR(G31:L31),0) -> -0.0013364765
A32: Scenario A 4-4 | B32: =$B10 -> 18 | C32: =F$6 -> 18 | D32: ='Rights Basis'!$B$11*B32 -> 19925100 | E32: =D32*Assumptions!$B$46 -> 12951315 | F32: =D32*(1+Assumptions!$B$48)-E32 -> 7272661.5 | G32: =-F32 -> -7272661.5 | H32: ='5Y Underwriting'!C18-MAX(0,E32*(1-(1-1)*Assumptions!$B$50))*Assumptions!$B$47-MIN(MAX(0,E32*(1-(1-1)*Assumptions!$B$50)),E32*Assumptions!$B$50) -> -60535.8 | I32: ='5Y Underwriting'!D18-MAX(0,E32*(1-(2-1)*Assumptions!$B$50))*Assumptions!$B$47-MIN(MAX(0,E32*(1-(2-1)*Assumptions!$B$50)),E32*Assumptions!$B$50) -> -44217.688 | J32: ='5Y Underwriting'!E18-MAX(0,E32*(1-(3-1)*Assumptions!$B$50))*Assumptions!$B$47-MIN(MAX(0,E32*(1-(3-1)*Assumptions!$B$50)),E32*Assumptions!$B$50) -> -27413.568 | K32: ='5Y Underwriting'!F18-MAX(0,E32*(1-(4-1)*Assumptions!$B$50))*Assumptions!$B$47-MIN(MAX(0,E32*(1-(4-1)*Assumptions!$B$50)),E32*Assumptions!$B$50) -> -10111.434 | L32: ='5Y Underwriting'!G18-MAX(0,E32*(1-(5-1)*Assumptions!$B$50))*Assumptions!$B$47-MIN(MAX(0,E32*(1-(5-1)*Assumptions!$B$50)),E32*Assumptions!$B$50)+'5Y Underwriting'!$G$16*C32*(1-Assumptions!$B$49)-MAX(0,E32*(1-5*Assumptions!$B$50)) -> 8560560.6 | M32: =IFERROR(IRR(G32:L32),0) -> 0.029361601
A33: Scenario A 4-5 | B33: =$B10 -> 18 | C33: =G$6 -> 19 | D33: ='Rights Basis'!$B$11*B33 -> 19925100 | E33: =D33*Assumptions!$B$46 -> 12951315 | F33: =D33*(1+Assumptions!$B$48)-E33 -> 7272661.5 | G33: =-F33 -> -7272661.5 | H33: ='5Y Underwriting'!C18-MAX(0,E33*(1-(1-1)*Assumptions!$B$50))*Assumptions!$B$47-MIN(MAX(0,E33*(1-(1-1)*Assumptions!$B$50)),E33*Assumptions!$B$50) -> -60535.8 | I33: ='5Y Underwriting'!D18-MAX(0,E33*(1-(2-1)*Assumptions!$B$50))*Assumptions!$B$47-MIN(MAX(0,E33*(1-(2-1)*Assumptions!$B$50)),E33*Assumptions!$B$50) -> -44217.688 | J33: ='5Y Underwriting'!E18-MAX(0,E33*(1-(3-1)*Assumptions!$B$50))*Assumptions!$B$47-MIN(MAX(0,E33*(1-(3-1)*Assumptions!$B$50)),E33*Assumptions!$B$50) -> -27413.568 | K33: ='5Y Underwriting'!F18-MAX(0,E33*(1-(4-1)*Assumptions!$B$50))*Assumptions!$B$47-MIN(MAX(0,E33*(1-(4-1)*Assumptions!$B$50)),E33*Assumptions!$B$50) -> -10111.434 | L33: ='5Y Underwriting'!G18-MAX(0,E33*(1-(5-1)*Assumptions!$B$50))*Assumptions!$B$47-MIN(MAX(0,E33*(1-(5-1)*Assumptions!$B$50)),E33*Assumptions!$B$50)+'5Y Underwriting'!$G$16*C33*(1-Assumptions!$B$49)-MAX(0,E33*(1-5*Assumptions!$B$50)) -> 9755237 | M33: =IFERROR(IRR(G33:L33),0) -> 0.056795625
A34: Scenario A 5-1 | B34: =$B11 -> 19 | C34: =C$6 -> 15 | D34: ='Rights Basis'!$B$11*B34 -> 21032050 | E34: =D34*Assumptions!$B$46 -> 13670832 | F34: =D34*(1+Assumptions!$B$48)-E34 -> 7676698.2 | G34: =-F34 -> -7676698.2 | H34: ='5Y Underwriting'!C18-MAX(0,E34*(1-(1-1)*Assumptions!$B$50))*Assumptions!$B$47-MIN(MAX(0,E34*(1-(1-1)*Assumptions!$B$50)),E34*Assumptions!$B$50) -> -110902.03 | I34: ='5Y Underwriting'!D18-MAX(0,E34*(1-(2-1)*Assumptions!$B$50))*Assumptions!$B$47-MIN(MAX(0,E34*(1-(2-1)*Assumptions!$B$50)),E34*Assumptions!$B$50) -> -94583.913 | J34: ='5Y Underwriting'!E18-MAX(0,E34*(1-(3-1)*Assumptions!$B$50))*Assumptions!$B$47-MIN(MAX(0,E34*(1-(3-1)*Assumptions!$B$50)),E34*Assumptions!$B$50) -> -77779.793 | K34: ='5Y Underwriting'!F18-MAX(0,E34*(1-(4-1)*Assumptions!$B$50))*Assumptions!$B$47-MIN(MAX(0,E34*(1-(4-1)*Assumptions!$B$50)),E34*Assumptions!$B$50) -> -60477.659 | L34: ='5Y Underwriting'!G18-MAX(0,E34*(1-(5-1)*Assumptions!$B$50))*Assumptions!$B$47-MIN(MAX(0,E34*(1-(5-1)*Assumptions!$B$50)),E34*Assumptions!$B$50)+'5Y Underwriting'!$G$16*C34*(1-Assumptions!$B$49)-MAX(0,E34*(1-5*Assumptions!$B$50)) -> 4206647.8 | M34: =IFERROR(IRR(G34:L34),0) -> -0.1237815
A35: Scenario A 5-2 | B35: =$B11 -> 19 | C35: =D$6 -> 16 | D35: ='Rights Basis'!$B$11*B35 -> 21032050 | E35: =D35*Assumptions!$B$46 -> 13670832 | F35: =D35*(1+Assumptions!$B$48)-E35 -> 7676698.2 | G35: =-F35 -> -7676698.2 | H35: ='5Y Underwriting'!C18-MAX(0,E35*(1-(1-1)*Assumptions!$B$50))*Assumptions!$B$47-MIN(MAX(0,E35*(1-(1-1)*Assumptions!$B$50)),E35*Assumptions!$B$50) -> -110902.03 | I35: ='5Y Underwriting'!D18-MAX(0,E35*(1-(2-1)*Assumptions!$B$50))*Assumptions!$B$47-MIN(MAX(0,E35*(1-(2-1)*Assumptions!$B$50)),E35*Assumptions!$B$50) -> -94583.913 | J35: ='5Y Underwriting'!E18-MAX(0,E35*(1-(3-1)*Assumptions!$B$50))*Assumptions!$B$47-MIN(MAX(0,E35*(1-(3-1)*Assumptions!$B$50)),E35*Assumptions!$B$50) -> -77779.793 | K35: ='5Y Underwriting'!F18-MAX(0,E35*(1-(4-1)*Assumptions!$B$50))*Assumptions!$B$47-MIN(MAX(0,E35*(1-(4-1)*Assumptions!$B$50)),E35*Assumptions!$B$50) -> -60477.659 | L35: ='5Y Underwriting'!G18-MAX(0,E35*(1-(5-1)*Assumptions!$B$50))*Assumptions!$B$47-MIN(MAX(0,E35*(1-(5-1)*Assumptions!$B$50)),E35*Assumptions!$B$50)+'5Y Underwriting'!$G$16*C35*(1-Assumptions!$B$49)-MAX(0,E35*(1-5*Assumptions!$B$50)) -> 5401324.2 | M35: =IFERROR(IRR(G35:L35),0) -> -0.077637014
A36: Scenario A 5-3 | B36: =$B11 -> 19 | C36: =E$6 -> 17 | D36: ='Rights Basis'!$B$11*B36 -> 21032050 | E36: =D36*Assumptions!$B$46 -> 13670832 | F36: =D36*(1+Assumptions!$B$48)-E36 -> 7676698.2 | G36: =-F36 -> -7676698.2 | H36: ='5Y Underwriting'!C18-MAX(0,E36*(1-(1-1)*Assumptions!$B$50))*Assumptions!$B$47-MIN(MAX(0,E36*(1-(1-1)*Assumptions!$B$50)),E36*Assumptions!$B$50) -> -110902.03 | I36: ='5Y Underwriting'!D18-MAX(0,E36*(1-(2-1)*Assumptions!$B$50))*Assumptions!$B$47-MIN(MAX(0,E36*(1-(2-1)*Assumptions!$B$50)),E36*Assumptions!$B$50) -> -94583.913 | J36: ='5Y Underwriting'!E18-MAX(0,E36*(1-(3-1)*Assumptions!$B$50))*Assumptions!$B$47-MIN(MAX(0,E36*(1-(3-1)*Assumptions!$B$50)),E36*Assumptions!$B$50) -> -77779.793 | K36: ='5Y Underwriting'!F18-MAX(0,E36*(1-(4-1)*Assumptions!$B$50))*Assumptions!$B$47-MIN(MAX(0,E36*(1-(4-1)*Assumptions!$B$50)),E36*Assumptions!$B$50) -> -60477.659 | L36: ='5Y Underwriting'!G18-MAX(0,E36*(1-(5-1)*Assumptions!$B$50))*Assumptions!$B$47-MIN(MAX(0,E36*(1-(5-1)*Assumptions!$B$50)),E36*Assumptions!$B$50)+'5Y Underwriting'!$G$16*C36*(1-Assumptions!$B$49)-MAX(0,E36*(1-5*Assumptions!$B$50)) -> 6596000.5 | M36: =IFERROR(IRR(G36:L36),0) -> -0.039134542
A37: Scenario A 5-4 | B37: =$B11 -> 19 | C37: =F$6 -> 18 | D37: ='Rights Basis'!$B$11*B37 -> 21032050 | E37: =D37*Assumptions!$B$46 -> 13670832 | F37: =D37*(1+Assumptions!$B$48)-E37 -> 7676698.2 | G37: =-F37 -> -7676698.2 | H37: ='5Y Underwriting'!C18-MAX(0,E37*(1-(1-1)*Assumptions!$B$50))*Assumptions!$B$47-MIN(MAX(0,E37*(1-(1-1)*Assumptions!$B$50)),E37*Assumptions!$B$50) -> -110902.03 | I37: ='5Y Underwriting'!D18-MAX(0,E37*(1-(2-1)*Assumptions!$B$50))*Assumptions!$B$47-MIN(MAX(0,E37*(1-(2-1)*Assumptions!$B$50)),E37*Assumptions!$B$50) -> -94583.913 | J37: ='5Y Underwriting'!E18-MAX(0,E37*(1-(3-1)*Assumptions!$B$50))*Assumptions!$B$47-MIN(MAX(0,E37*(1-(3-1)*Assumptions!$B$50)),E37*Assumptions!$B$50) -> -77779.793 | K37: ='5Y Underwriting'!F18-MAX(0,E37*(1-(4-1)*Assumptions!$B$50))*Assumptions!$B$47-MIN(MAX(0,E37*(1-(4-1)*Assumptions!$B$50)),E37*Assumptions!$B$50) -> -60477.659 | L37: ='5Y Underwriting'!G18-MAX(0,E37*(1-(5-1)*Assumptions!$B$50))*Assumptions!$B$47-MIN(MAX(0,E37*(1-(5-1)*Assumptions!$B$50)),E37*Assumptions!$B$50)+'5Y Underwriting'!$G$16*C37*(1-Assumptions!$B$49)-MAX(0,E37*(1-5*Assumptions!$B$50)) -> 7790676.9 | M37: =IFERROR(IRR(G37:L37),0) -> -0.0059111486
A38: Scenario A 5-5 | B38: =$B11 -> 19 | C38: =G$6 -> 19 | D38: ='Rights Basis'!$B$11*B38 -> 21032050 | E38: =D38*Assumptions!$B$46 -> 13670832 | F38: =D38*(1+Assumptions!$B$48)-E38 -> 7676698.2 | G38: =-F38 -> -7676698.2 | H38: ='5Y Underwriting'!C18-MAX(0,E38*(1-(1-1)*Assumptions!$B$50))*Assumptions!$B$47-MIN(MAX(0,E38*(1-(1-1)*Assumptions!$B$50)),E38*Assumptions!$B$50) -> -110902.03 | I38: ='5Y Underwriting'!D18-MAX(0,E38*(1-(2-1)*Assumptions!$B$50))*Assumptions!$B$47-MIN(MAX(0,E38*(1-(2-1)*Assumptions!$B$50)),E38*Assumptions!$B$50) -> -94583.913 | J38: ='5Y Underwriting'!E18-MAX(0,E38*(1-(3-1)*Assumptions!$B$50))*Assumptions!$B$47-MIN(MAX(0,E38*(1-(3-1)*Assumptions!$B$50)),E38*Assumptions!$B$50) -> -77779.793 | K38: ='5Y Underwriting'!F18-MAX(0,E38*(1-(4-1)*Assumptions!$B$50))*Assumptions!$B$47-MIN(MAX(0,E38*(1-(4-1)*Assumptions!$B$50)),E38*Assumptions!$B$50) -> -60477.659 | L38: ='5Y Underwriting'!G18-MAX(0,E38*(1-(5-1)*Assumptions!$B$50))*Assumptions!$B$47-MIN(MAX(0,E38*(1-(5-1)*Assumptions!$B$50)),E38*Assumptions!$B$50)+'5Y Underwriting'!$G$16*C38*(1-Assumptions!$B$49)-MAX(0,E38*(1-5*Assumptions!$B$50)) -> 8985353.3 | M38: =IFERROR(IRR(G38:L38),0) -> 0.023424676
A41: SCENARIO B | DEBT PERCENTAGE × INTEREST RATE
A43: Debt proportion ↓ / annual borrowing cost →
C44: =Assumptions!$B$47+(0-2)*0.01 -> 0.05 | D44: =Assumptions!$B$47+(1-2)*0.01 -> 0.06 | E44: =Assumptions!$B$47+(2-2)*0.01 -> 0.07 | F44: =Assumptions!$B$47+(3-2)*0.01 -> 0.08 | G44: =Assumptions!$B$47+(4-2)*0.01 -> 0.09
B45: =Assumptions!$B$46+(0-2)*0.05 -> 0.55 | C45: =M52 -> 0.065392242 | D45: =M53 -> 0.054155569 | E45: =M54 -> 0.042931526 | F45: =M55 -> 0.031720296 | G45: =M56 -> 0.02052206
B46: =Assumptions!$B$46+(1-2)*0.05 -> 0.6 | C46: =M57 -> 0.067144729 | D46: =M58 -> 0.053491065 | E46: =M59 -> 0.039858182 | F46: =M60 -> 0.026246433 | G46: =M61 -> 0.012656166
B47: =Assumptions!$B$46+(2-2)*0.05 -> 0.65 | C47: =M62 -> 0.069348086 | D47: =M63 -> 0.052656149 | E47: =M64 -> 0.035999276 | F47: =M65 -> 0.01937817 | G47: =M66 -> 0.0027935074
B48: =Assumptions!$B$46+(3-2)*0.05 -> 0.7 | C48: =M67 -> 0.072202304 | D48: =M68 -> 0.051575671 | E48: =M69 -> 0.031010501 | F48: =M70 -> 0.010508228 | G48: =M71 -> -0.009929784
B49: =Assumptions!$B$46+(4-2)*0.05 -> 0.75 | C49: =M72 -> 0.076046473 | D49: =M73 -> 0.050122726 | E49: =M74 -> 0.024312877 | F49: =M75 -> -0.0013800009 | G49: =M76 -> -0.026953081
A52: Scenario B 1-1 | B52: =$B45 -> 0.55 | C52: =C$44 -> 0.05 | D52: ='Sources & Uses'!$B$7 -> 18818150 | E52: =D52*B52 -> 10349982 | F52: =D52*(1+Assumptions!$B$48)-E52 -> 8750439.8 | G52: =-F52 -> -8750439.8 | H52: ='5Y Underwriting'!C18-MAX(0,E52*(1-(1-1)*Assumptions!$B$50))*C52-MIN(MAX(0,E52*(1-(1-1)*Assumptions!$B$50)),E52*Assumptions!$B$50) -> 328557.12 | I52: ='5Y Underwriting'!D18-MAX(0,E52*(1-(2-1)*Assumptions!$B$50))*C52-MIN(MAX(0,E52*(1-(2-1)*Assumptions!$B$50)),E52*Assumptions!$B$50) -> 344875.24 | J52: ='5Y Underwriting'!E18-MAX(0,E52*(1-(3-1)*Assumptions!$B$50))*C52-MIN(MAX(0,E52*(1-(3-1)*Assumptions!$B$50)),E52*Assumptions!$B$50) -> 361679.36 | K52: ='5Y Underwriting'!F18-MAX(0,E52*(1-(4-1)*Assumptions!$B$50))*C52-MIN(MAX(0,E52*(1-(4-1)*Assumptions!$B$50)),E52*Assumptions!$B$50) -> 378981.49 | L52: ='5Y Underwriting'!G18-MAX(0,E52*(1-(5-1)*Assumptions!$B$50))*C52-MIN(MAX(0,E52*(1-(5-1)*Assumptions!$B$50)),E52*Assumptions!$B$50)+'5Y Underwriting'!$G$16*Assumptions!$B$45*(1-Assumptions!$B$49)-MAX(0,E52*(1-5*Assumptions!$B$50)) -> 10356310 | M52: =IFERROR(IRR(G52:L52),0) -> 0.065392242
A53: Scenario B 1-2 | B53: =$B45 -> 0.55 | C53: =D$44 -> 0.06 | D53: ='Sources & Uses'!$B$7 -> 18818150 | E53: =D53*B53 -> 10349982 | F53: =D53*(1+Assumptions!$B$48)-E53 -> 8750439.8 | G53: =-F53 -> -8750439.8 | H53: ='5Y Underwriting'!C18-MAX(0,E53*(1-(1-1)*Assumptions!$B$50))*C53-MIN(MAX(0,E53*(1-(1-1)*Assumptions!$B$50)),E53*Assumptions!$B$50) -> 225057.3 | I53: ='5Y Underwriting'!D18-MAX(0,E53*(1-(2-1)*Assumptions!$B$50))*C53-MIN(MAX(0,E53*(1-(2-1)*Assumptions!$B$50)),E53*Assumptions!$B$50) -> 241375.41 | J53: ='5Y Underwriting'!E18-MAX(0,E53*(1-(3-1)*Assumptions!$B$50))*C53-MIN(MAX(0,E53*(1-(3-1)*Assumptions!$B$50)),E53*Assumptions!$B$50) -> 258179.53 | K53: ='5Y Underwriting'!F18-MAX(0,E53*(1-(4-1)*Assumptions!$B$50))*C53-MIN(MAX(0,E53*(1-(4-1)*Assumptions!$B$50)),E53*Assumptions!$B$50) -> 275481.67 | L53: ='5Y Underwriting'!G18-MAX(0,E53*(1-(5-1)*Assumptions!$B$50))*C53-MIN(MAX(0,E53*(1-(5-1)*Assumptions!$B$50)),E53*Assumptions!$B$50)+'5Y Underwriting'!$G$16*Assumptions!$B$45*(1-Assumptions!$B$49)-MAX(0,E53*(1-5*Assumptions!$B$50)) -> 10252810 | M53: =IFERROR(IRR(G53:L53),0) -> 0.054155569
A54: Scenario B 1-3 | B54: =$B45 -> 0.55 | C54: =E$44 -> 0.07 | D54: ='Sources & Uses'!$B$7 -> 18818150 | E54: =D54*B54 -> 10349982 | F54: =D54*(1+Assumptions!$B$48)-E54 -> 8750439.8 | G54: =-F54 -> -8750439.8 | H54: ='5Y Underwriting'!C18-MAX(0,E54*(1-(1-1)*Assumptions!$B$50))*C54-MIN(MAX(0,E54*(1-(1-1)*Assumptions!$B$50)),E54*Assumptions!$B$50) -> 121557.47 | I54: ='5Y Underwriting'!D18-MAX(0,E54*(1-(2-1)*Assumptions!$B$50))*C54-MIN(MAX(0,E54*(1-(2-1)*Assumptions!$B$50)),E54*Assumptions!$B$50) -> 137875.59 | J54: ='5Y Underwriting'!E18-MAX(0,E54*(1-(3-1)*Assumptions!$B$50))*C54-MIN(MAX(0,E54*(1-(3-1)*Assumptions!$B$50)),E54*Assumptions!$B$50) -> 154679.71 | K54: ='5Y Underwriting'!F18-MAX(0,E54*(1-(4-1)*Assumptions!$B$50))*C54-MIN(MAX(0,E54*(1-(4-1)*Assumptions!$B$50)),E54*Assumptions!$B$50) -> 171981.84 | L54: ='5Y Underwriting'!G18-MAX(0,E54*(1-(5-1)*Assumptions!$B$50))*C54-MIN(MAX(0,E54*(1-(5-1)*Assumptions!$B$50)),E54*Assumptions!$B$50)+'5Y Underwriting'!$G$16*Assumptions!$B$45*(1-Assumptions!$B$49)-MAX(0,E54*(1-5*Assumptions!$B$50)) -> 10149310 | M54: =IFERROR(IRR(G54:L54),0) -> 0.042931526
A55: Scenario B 1-4 | B55: =$B45 -> 0.55 | C55: =F$44 -> 0.08 | D55: ='Sources & Uses'!$B$7 -> 18818150 | E55: =D55*B55 -> 10349982 | F55: =D55*(1+Assumptions!$B$48)-E55 -> 8750439.8 | G55: =-F55 -> -8750439.8 | H55: ='5Y Underwriting'!C18-MAX(0,E55*(1-(1-1)*Assumptions!$B$50))*C55-MIN(MAX(0,E55*(1-(1-1)*Assumptions!$B$50)),E55*Assumptions!$B$50) -> 18057.65 | I55: ='5Y Underwriting'!D18-MAX(0,E55*(1-(2-1)*Assumptions!$B$50))*C55-MIN(MAX(0,E55*(1-(2-1)*Assumptions!$B$50)),E55*Assumptions!$B$50) -> 34375.762 | J55: ='5Y Underwriting'!E18-MAX(0,E55*(1-(3-1)*Assumptions!$B$50))*C55-MIN(MAX(0,E55*(1-(3-1)*Assumptions!$B$50)),E55*Assumptions!$B$50) -> 51179.882 | K55: ='5Y Underwriting'!F18-MAX(0,E55*(1-(4-1)*Assumptions!$B$50))*C55-MIN(MAX(0,E55*(1-(4-1)*Assumptions!$B$50)),E55*Assumptions!$B$50) -> 68482.016 | L55: ='5Y Underwriting'!G18-MAX(0,E55*(1-(5-1)*Assumptions!$B$50))*C55-MIN(MAX(0,E55*(1-(5-1)*Assumptions!$B$50)),E55*Assumptions!$B$50)+'5Y Underwriting'!$G$16*Assumptions!$B$45*(1-Assumptions!$B$49)-MAX(0,E55*(1-5*Assumptions!$B$50)) -> 10045810 | M55: =IFERROR(IRR(G55:L55),0) -> 0.031720296
A56: Scenario B 1-5 | B56: =$B45 -> 0.55 | C56: =G$44 -> 0.09 | D56: ='Sources & Uses'!$B$7 -> 18818150 | E56: =D56*B56 -> 10349982 | F56: =D56*(1+Assumptions!$B$48)-E56 -> 8750439.8 | G56: =-F56 -> -8750439.8 | H56: ='5Y Underwriting'!C18-MAX(0,E56*(1-(1-1)*Assumptions!$B$50))*C56-MIN(MAX(0,E56*(1-(1-1)*Assumptions!$B$50)),E56*Assumptions!$B$50) -> -85442.175 | I56: ='5Y Underwriting'!D18-MAX(0,E56*(1-(2-1)*Assumptions!$B$50))*C56-MIN(MAX(0,E56*(1-(2-1)*Assumptions!$B$50)),E56*Assumptions!$B$50) -> -69124.063 | J56: ='5Y Underwriting'!E18-MAX(0,E56*(1-(3-1)*Assumptions!$B$50))*C56-MIN(MAX(0,E56*(1-(3-1)*Assumptions!$B$50)),E56*Assumptions!$B$50) -> -52319.943 | K56: ='5Y Underwriting'!F18-MAX(0,E56*(1-(4-1)*Assumptions!$B$50))*C56-MIN(MAX(0,E56*(1-(4-1)*Assumptions!$B$50)),E56*Assumptions!$B$50) -> -35017.809 | L56: ='5Y Underwriting'!G18-MAX(0,E56*(1-(5-1)*Assumptions!$B$50))*C56-MIN(MAX(0,E56*(1-(5-1)*Assumptions!$B$50)),E56*Assumptions!$B$50)+'5Y Underwriting'!$G$16*Assumptions!$B$45*(1-Assumptions!$B$49)-MAX(0,E56*(1-5*Assumptions!$B$50)) -> 9942310.4 | M56: =IFERROR(IRR(G56:L56),0) -> 0.02052206
A57: Scenario B 2-1 | B57: =$B46 -> 0.6 | C57: =C$44 -> 0.05 | D57: ='Sources & Uses'!$B$7 -> 18818150 | E57: =D57*B57 -> 11290890 | F57: =D57*(1+Assumptions!$B$48)-E57 -> 7809532.2 | G57: =-F57 -> -7809532.2 | H57: ='5Y Underwriting'!C18-MAX(0,E57*(1-(1-1)*Assumptions!$B$50))*C57-MIN(MAX(0,E57*(1-(1-1)*Assumptions!$B$50)),E57*Assumptions!$B$50) -> 281511.75 | I57: ='5Y Underwriting'!D18-MAX(0,E57*(1-(2-1)*Assumptions!$B$50))*C57-MIN(MAX(0,E57*(1-(2-1)*Assumptions!$B$50)),E57*Assumptions!$B$50) -> 297829.86 | J57: ='5Y Underwriting'!E18-MAX(0,E57*(1-(3-1)*Assumptions!$B$50))*C57-MIN(MAX(0,E57*(1-(3-1)*Assumptions!$B$50)),E57*Assumptions!$B$50) -> 314633.98 | K57: ='5Y Underwriting'!F18-MAX(0,E57*(1-(4-1)*Assumptions!$B$50))*C57-MIN(MAX(0,E57*(1-(4-1)*Assumptions!$B$50)),E57*Assumptions!$B$50) -> 331936.12 | L57: ='5Y Underwriting'!G18-MAX(0,E57*(1-(5-1)*Assumptions!$B$50))*C57-MIN(MAX(0,E57*(1-(5-1)*Assumptions!$B$50)),E57*Assumptions!$B$50)+'5Y Underwriting'!$G$16*Assumptions!$B$45*(1-Assumptions!$B$49)-MAX(0,E57*(1-5*Assumptions!$B$50)) -> 9368356.8 | M57: =IFERROR(IRR(G57:L57),0) -> 0.067144729
A58: Scenario B 2-2 | B58: =$B46 -> 0.6 | C58: =D$44 -> 0.06 | D58: ='Sources & Uses'!$B$7 -> 18818150 | E58: =D58*B58 -> 11290890 | F58: =D58*(1+Assumptions!$B$48)-E58 -> 7809532.2 | G58: =-F58 -> -7809532.2 | H58: ='5Y Underwriting'!C18-MAX(0,E58*(1-(1-1)*Assumptions!$B$50))*C58-MIN(MAX(0,E58*(1-(1-1)*Assumptions!$B$50)),E58*Assumptions!$B$50) -> 168602.85 | I58: ='5Y Underwriting'!D18-MAX(0,E58*(1-(2-1)*Assumptions!$B$50))*C58-MIN(MAX(0,E58*(1-(2-1)*Assumptions!$B$50)),E58*Assumptions!$B$50) -> 184920.96 | J58: ='5Y Underwriting'!E18-MAX(0,E58*(1-(3-1)*Assumptions!$B$50))*C58-MIN(MAX(0,E58*(1-(3-1)*Assumptions!$B$50)),E58*Assumptions!$B$50) -> 201725.08 | K58: ='5Y Underwriting'!F18-MAX(0,E58*(1-(4-1)*Assumptions!$B$50))*C58-MIN(MAX(0,E58*(1-(4-1)*Assumptions!$B$50)),E58*Assumptions!$B$50) -> 219027.22 | L58: ='5Y Underwriting'!G18-MAX(0,E58*(1-(5-1)*Assumptions!$B$50))*C58-MIN(MAX(0,E58*(1-(5-1)*Assumptions!$B$50)),E58*Assumptions!$B$50)+'5Y Underwriting'!$G$16*Assumptions!$B$45*(1-Assumptions!$B$49)-MAX(0,E58*(1-5*Assumptions!$B$50)) -> 9255447.9 | M58: =IFERROR(IRR(G58:L58),0) -> 0.053491065
A59: Scenario B 2-3 | B59: =$B46 -> 0.6 | C59: =E$44 -> 0.07 | D59: ='Sources & Uses'!$B$7 -> 18818150 | E59: =D59*B59 -> 11290890 | F59: =D59*(1+Assumptions!$B$48)-E59 -> 7809532.2 | G59: =-F59 -> -7809532.2 | H59: ='5Y Underwriting'!C18-MAX(0,E59*(1-(1-1)*Assumptions!$B$50))*C59-MIN(MAX(0,E59*(1-(1-1)*Assumptions!$B$50)),E59*Assumptions!$B$50) -> 55693.95 | I59: ='5Y Underwriting'!D18-MAX(0,E59*(1-(2-1)*Assumptions!$B$50))*C59-MIN(MAX(0,E59*(1-(2-1)*Assumptions!$B$50)),E59*Assumptions!$B$50) -> 72012.062 | J59: ='5Y Underwriting'!E18-MAX(0,E59*(1-(3-1)*Assumptions!$B$50))*C59-MIN(MAX(0,E59*(1-(3-1)*Assumptions!$B$50)),E59*Assumptions!$B$50) -> 88816.182 | K59: ='5Y Underwriting'!F18-MAX(0,E59*(1-(4-1)*Assumptions!$B$50))*C59-MIN(MAX(0,E59*(1-(4-1)*Assumptions!$B$50)),E59*Assumptions!$B$50) -> 106118.32 | L59: ='5Y Underwriting'!G18-MAX(0,E59*(1-(5-1)*Assumptions!$B$50))*C59-MIN(MAX(0,E59*(1-(5-1)*Assumptions!$B$50)),E59*Assumptions!$B$50)+'5Y Underwriting'!$G$16*Assumptions!$B$45*(1-Assumptions!$B$49)-MAX(0,E59*(1-5*Assumptions!$B$50)) -> 9142539 | M59: =IFERROR(IRR(G59:L59),0) -> 0.039858182
A60: Scenario B 2-4 | B60: =$B46 -> 0.6 | C60: =F$44 -> 0.08 | D60: ='Sources & Uses'!$B$7 -> 18818150 | E60: =D60*B60 -> 11290890 | F60: =D60*(1+Assumptions!$B$48)-E60 -> 7809532.2 | G60: =-F60 -> -7809532.2 | H60: ='5Y Underwriting'!C18-MAX(0,E60*(1-(1-1)*Assumptions!$B$50))*C60-MIN(MAX(0,E60*(1-(1-1)*Assumptions!$B$50)),E60*Assumptions!$B$50) -> -57214.95 | I60: ='5Y Underwriting'!D18-MAX(0,E60*(1-(2-1)*Assumptions!$B$50))*C60-MIN(MAX(0,E60*(1-(2-1)*Assumptions!$B$50)),E60*Assumptions!$B$50) -> -40896.838 | J60: ='5Y Underwriting'!E18-MAX(0,E60*(1-(3-1)*Assumptions!$B$50))*C60-MIN(MAX(0,E60*(1-(3-1)*Assumptions!$B$50)),E60*Assumptions!$B$50) -> -24092.718 | K60: ='5Y Underwriting'!F18-MAX(0,E60*(1-(4-1)*Assumptions!$B$50))*C60-MIN(MAX(0,E60*(1-(4-1)*Assumptions!$B$50)),E60*Assumptions!$B$50) -> -6790.584 | L60: ='5Y Underwriting'!G18-MAX(0,E60*(1-(5-1)*Assumptions!$B$50))*C60-MIN(MAX(0,E60*(1-(5-1)*Assumptions!$B$50)),E60*Assumptions!$B$50)+'5Y Underwriting'!$G$16*Assumptions!$B$45*(1-Assumptions!$B$49)-MAX(0,E60*(1-5*Assumptions!$B$50)) -> 9029630.1 | M60: =IFERROR(IRR(G60:L60),0) -> 0.026246433
A61: Scenario B 2-5 | B61: =$B46 -> 0.6 | C61: =G$44 -> 0.09 | D61: ='Sources & Uses'!$B$7 -> 18818150 | E61: =D61*B61 -> 11290890 | F61: =D61*(1+Assumptions!$B$48)-E61 -> 7809532.2 | G61: =-F61 -> -7809532.2 | H61: ='5Y Underwriting'!C18-MAX(0,E61*(1-(1-1)*Assumptions!$B$50))*C61-MIN(MAX(0,E61*(1-(1-1)*Assumptions!$B$50)),E61*Assumptions!$B$50) -> -170123.85 | I61: ='5Y Underwriting'!D18-MAX(0,E61*(1-(2-1)*Assumptions!$B$50))*C61-MIN(MAX(0,E61*(1-(2-1)*Assumptions!$B$50)),E61*Assumptions!$B$50) -> -153805.74 | J61: ='5Y Underwriting'!E18-MAX(0,E61*(1-(3-1)*Assumptions!$B$50))*C61-MIN(MAX(0,E61*(1-(3-1)*Assumptions!$B$50)),E61*Assumptions!$B$50) -> -137001.62 | K61: ='5Y Underwriting'!F18-MAX(0,E61*(1-(4-1)*Assumptions!$B$50))*C61-MIN(MAX(0,E61*(1-(4-1)*Assumptions!$B$50)),E61*Assumptions!$B$50) -> -119699.48 | L61: ='5Y Underwriting'!G18-MAX(0,E61*(1-(5-1)*Assumptions!$B$50))*C61-MIN(MAX(0,E61*(1-(5-1)*Assumptions!$B$50)),E61*Assumptions!$B$50)+'5Y Underwriting'!$G$16*Assumptions!$B$45*(1-Assumptions!$B$49)-MAX(0,E61*(1-5*Assumptions!$B$50)) -> 8916721.2 | M61: =IFERROR(IRR(G61:L61),0) -> 0.012656166
A62: Scenario B 3-1 | B62: =$B47 -> 0.65 | C62: =C$44 -> 0.05 | D62: ='Sources & Uses'!$B$7 -> 18818150 | E62: =D62*B62 -> 12231798 | F62: =D62*(1+Assumptions!$B$48)-E62 -> 6868624.8 | G62: =-F62 -> -6868624.8 | H62: ='5Y Underwriting'!C18-MAX(0,E62*(1-(1-1)*Assumptions!$B$50))*C62-MIN(MAX(0,E62*(1-(1-1)*Assumptions!$B$50)),E62*Assumptions!$B$50) -> 234466.38 | I62: ='5Y Underwriting'!D18-MAX(0,E62*(1-(2-1)*Assumptions!$B$50))*C62-MIN(MAX(0,E62*(1-(2-1)*Assumptions!$B$50)),E62*Assumptions!$B$50) -> 250784.49 | J62: ='5Y Underwriting'!E18-MAX(0,E62*(1-(3-1)*Assumptions!$B$50))*C62-MIN(MAX(0,E62*(1-(3-1)*Assumptions!$B$50)),E62*Assumptions!$B$50) -> 267588.61 | K62: ='5Y Underwriting'!F18-MAX(0,E62*(1-(4-1)*Assumptions!$B$50))*C62-MIN(MAX(0,E62*(1-(4-1)*Assumptions!$B$50)),E62*Assumptions!$B$50) -> 284890.74 | L62: ='5Y Underwriting'!G18-MAX(0,E62*(1-(5-1)*Assumptions!$B$50))*C62-MIN(MAX(0,E62*(1-(5-1)*Assumptions!$B$50)),E62*Assumptions!$B$50)+'5Y Underwriting'!$G$16*Assumptions!$B$45*(1-Assumptions!$B$49)-MAX(0,E62*(1-5*Assumptions!$B$50)) -> 8380403.9 | M62: =IFERROR(IRR(G62:L62),0) -> 0.069348086
A63: Scenario B 3-2 | B63: =$B47 -> 0.65 | C63: =D$44 -> 0.06 | D63: ='Sources & Uses'!$B$7 -> 18818150 | E63: =D63*B63 -> 12231798 | F63: =D63*(1+Assumptions!$B$48)-E63 -> 6868624.8 | G63: =-F63 -> -6868624.8 | H63: ='5Y Underwriting'!C18-MAX(0,E63*(1-(1-1)*Assumptions!$B$50))*C63-MIN(MAX(0,E63*(1-(1-1)*Assumptions!$B$50)),E63*Assumptions!$B$50) -> 112148.4 | I63: ='5Y Underwriting'!D18-MAX(0,E63*(1-(2-1)*Assumptions!$B$50))*C63-MIN(MAX(0,E63*(1-(2-1)*Assumptions!$B$50)),E63*Assumptions!$B$50) -> 128466.51 | J63: ='5Y Underwriting'!E18-MAX(0,E63*(1-(3-1)*Assumptions!$B$50))*C63-MIN(MAX(0,E63*(1-(3-1)*Assumptions!$B$50)),E63*Assumptions!$B$50) -> 145270.63 | K63: ='5Y Underwriting'!F18-MAX(0,E63*(1-(4-1)*Assumptions!$B$50))*C63-MIN(MAX(0,E63*(1-(4-1)*Assumptions!$B$50)),E63*Assumptions!$B$50) -> 162572.77 | L63: ='5Y Underwriting'!G18-MAX(0,E63*(1-(5-1)*Assumptions!$B$50))*C63-MIN(MAX(0,E63*(1-(5-1)*Assumptions!$B$50)),E63*Assumptions!$B$50)+'5Y Underwriting'!$G$16*Assumptions!$B$45*(1-Assumptions!$B$49)-MAX(0,E63*(1-5*Assumptions!$B$50)) -> 8258086 | M63: =IFERROR(IRR(G63:L63),0) -> 0.052656149
A64: Scenario B 3-3 | B64: =$B47 -> 0.65 | C64: =E$44 -> 0.07 | D64: ='Sources & Uses'!$B$7 -> 18818150 | E64: =D64*B64 -> 12231798 | F64: =D64*(1+Assumptions!$B$48)-E64 -> 6868624.8 | G64: =-F64 -> -6868624.8 | H64: ='5Y Underwriting'!C18-MAX(0,E64*(1-(1-1)*Assumptions!$B$50))*C64-MIN(MAX(0,E64*(1-(1-1)*Assumptions!$B$50)),E64*Assumptions!$B$50) -> -10169.575 | I64: ='5Y Underwriting'!D18-MAX(0,E64*(1-(2-1)*Assumptions!$B$50))*C64-MIN(MAX(0,E64*(1-(2-1)*Assumptions!$B$50)),E64*Assumptions!$B$50) -> 6148.5369 | J64: ='5Y Underwriting'!E18-MAX(0,E64*(1-(3-1)*Assumptions!$B$50))*C64-MIN(MAX(0,E64*(1-(3-1)*Assumptions!$B$50)),E64*Assumptions!$B$50) -> 22952.657 | K64: ='5Y Underwriting'!F18-MAX(0,E64*(1-(4-1)*Assumptions!$B$50))*C64-MIN(MAX(0,E64*(1-(4-1)*Assumptions!$B$50)),E64*Assumptions!$B$50) -> 40254.791 | L64: ='5Y Underwriting'!G18-MAX(0,E64*(1-(5-1)*Assumptions!$B$50))*C64-MIN(MAX(0,E64*(1-(5-1)*Assumptions!$B$50)),E64*Assumptions!$B$50)+'5Y Underwriting'!$G$16*Assumptions!$B$45*(1-Assumptions!$B$49)-MAX(0,E64*(1-5*Assumptions!$B$50)) -> 8135768 | M64: =IFERROR(IRR(G64:L64),0) -> 0.035999276
A65: Scenario B 3-4 | B65: =$B47 -> 0.65 | C65: =F$44 -> 0.08 | D65: ='Sources & Uses'!$B$7 -> 18818150 | E65: =D65*B65 -> 12231798 | F65: =D65*(1+Assumptions!$B$48)-E65 -> 6868624.8 | G65: =-F65 -> -6868624.8 | H65: ='5Y Underwriting'!C18-MAX(0,E65*(1-(1-1)*Assumptions!$B$50))*C65-MIN(MAX(0,E65*(1-(1-1)*Assumptions!$B$50)),E65*Assumptions!$B$50) -> -132487.55 | I65: ='5Y Underwriting'!D18-MAX(0,E65*(1-(2-1)*Assumptions!$B$50))*C65-MIN(MAX(0,E65*(1-(2-1)*Assumptions!$B$50)),E65*Assumptions!$B$50) -> -116169.44 | J65: ='5Y Underwriting'!E18-MAX(0,E65*(1-(3-1)*Assumptions!$B$50))*C65-MIN(MAX(0,E65*(1-(3-1)*Assumptions!$B$50)),E65*Assumptions!$B$50) -> -99365.318 | K65: ='5Y Underwriting'!F18-MAX(0,E65*(1-(4-1)*Assumptions!$B$50))*C65-MIN(MAX(0,E65*(1-(4-1)*Assumptions!$B$50)),E65*Assumptions!$B$50) -> -82063.184 | L65: ='5Y Underwriting'!G18-MAX(0,E65*(1-(5-1)*Assumptions!$B$50))*C65-MIN(MAX(0,E65*(1-(5-1)*Assumptions!$B$50)),E65*Assumptions!$B$50)+'5Y Underwriting'!$G$16*Assumptions!$B$45*(1-Assumptions!$B$49)-MAX(0,E65*(1-5*Assumptions!$B$50)) -> 8013450 | M65: =IFERROR(IRR(G65:L65),0) -> 0.01937817
A66: Scenario B 3-5 | B66: =$B47 -> 0.65 | C66: =G$44 -> 0.09 | D66: ='Sources & Uses'!$B$7 -> 18818150 | E66: =D66*B66 -> 12231798 | F66: =D66*(1+Assumptions!$B$48)-E66 -> 6868624.8 | G66: =-F66 -> -6868624.8 | H66: ='5Y Underwriting'!C18-MAX(0,E66*(1-(1-1)*Assumptions!$B$50))*C66-MIN(MAX(0,E66*(1-(1-1)*Assumptions!$B$50)),E66*Assumptions!$B$50) -> -254805.53 | I66: ='5Y Underwriting'!D18-MAX(0,E66*(1-(2-1)*Assumptions!$B$50))*C66-MIN(MAX(0,E66*(1-(2-1)*Assumptions!$B$50)),E66*Assumptions!$B$50) -> -238487.41 | J66: ='5Y Underwriting'!E18-MAX(0,E66*(1-(3-1)*Assumptions!$B$50))*C66-MIN(MAX(0,E66*(1-(3-1)*Assumptions!$B$50)),E66*Assumptions!$B$50) -> -221683.29 | K66: ='5Y Underwriting'!F18-MAX(0,E66*(1-(4-1)*Assumptions!$B$50))*C66-MIN(MAX(0,E66*(1-(4-1)*Assumptions!$B$50)),E66*Assumptions!$B$50) -> -204381.16 | L66: ='5Y Underwriting'!G18-MAX(0,E66*(1-(5-1)*Assumptions!$B$50))*C66-MIN(MAX(0,E66*(1-(5-1)*Assumptions!$B$50)),E66*Assumptions!$B$50)+'5Y Underwriting'!$G$16*Assumptions!$B$45*(1-Assumptions!$B$49)-MAX(0,E66*(1-5*Assumptions!$B$50)) -> 7891132 | M66: =IFERROR(IRR(G66:L66),0) -> 0.0027935074
A67: Scenario B 4-1 | B67: =$B48 -> 0.7 | C67: =C$44 -> 0.05 | D67: ='Sources & Uses'!$B$7 -> 18818150 | E67: =D67*B67 -> 13172705 | F67: =D67*(1+Assumptions!$B$48)-E67 -> 5927717.2 | G67: =-F67 -> -5927717.2 | H67: ='5Y Underwriting'!C18-MAX(0,E67*(1-(1-1)*Assumptions!$B$50))*C67-MIN(MAX(0,E67*(1-(1-1)*Assumptions!$B$50)),E67*Assumptions!$B$50) -> 187421 | I67: ='5Y Underwriting'!D18-MAX(0,E67*(1-(2-1)*Assumptions!$B$50))*C67-MIN(MAX(0,E67*(1-(2-1)*Assumptions!$B$50)),E67*Assumptions!$B$50) -> 203739.11 | J67: ='5Y Underwriting'!E18-MAX(0,E67*(1-(3-1)*Assumptions!$B$50))*C67-MIN(MAX(0,E67*(1-(3-1)*Assumptions!$B$50)),E67*Assumptions!$B$50) -> 220543.23 | K67: ='5Y Underwriting'!F18-MAX(0,E67*(1-(4-1)*Assumptions!$B$50))*C67-MIN(MAX(0,E67*(1-(4-1)*Assumptions!$B$50)),E67*Assumptions!$B$50) -> 237845.37 | L67: ='5Y Underwriting'!G18-MAX(0,E67*(1-(5-1)*Assumptions!$B$50))*C67-MIN(MAX(0,E67*(1-(5-1)*Assumptions!$B$50)),E67*Assumptions!$B$50)+'5Y Underwriting'!$G$16*Assumptions!$B$45*(1-Assumptions!$B$49)-MAX(0,E67*(1-5*Assumptions!$B$50)) -> 7392451.1 | M67: =IFERROR(IRR(G67:L67),0) -> 0.072202304
A68: Scenario B 4-2 | B68: =$B48 -> 0.7 | C68: =D$44 -> 0.06 | D68: ='Sources & Uses'!$B$7 -> 18818150 | E68: =D68*B68 -> 13172705 | F68: =D68*(1+Assumptions!$B$48)-E68 -> 5927717.2 | G68: =-F68 -> -5927717.2 | H68: ='5Y Underwriting'!C18-MAX(0,E68*(1-(1-1)*Assumptions!$B$50))*C68-MIN(MAX(0,E68*(1-(1-1)*Assumptions!$B$50)),E68*Assumptions!$B$50) -> 55693.95 | I68: ='5Y Underwriting'!D18-MAX(0,E68*(1-(2-1)*Assumptions!$B$50))*C68-MIN(MAX(0,E68*(1-(2-1)*Assumptions!$B$50)),E68*Assumptions!$B$50) -> 72012.062 | J68: ='5Y Underwriting'!E18-MAX(0,E68*(1-(3-1)*Assumptions!$B$50))*C68-MIN(MAX(0,E68*(1-(3-1)*Assumptions!$B$50)),E68*Assumptions!$B$50) -> 88816.182 | K68: ='5Y Underwriting'!F18-MAX(0,E68*(1-(4-1)*Assumptions!$B$50))*C68-MIN(MAX(0,E68*(1-(4-1)*Assumptions!$B$50)),E68*Assumptions!$B$50) -> 106118.32 | L68: ='5Y Underwriting'!G18-MAX(0,E68*(1-(5-1)*Assumptions!$B$50))*C68-MIN(MAX(0,E68*(1-(5-1)*Assumptions!$B$50)),E68*Assumptions!$B$50)+'5Y Underwriting'!$G$16*Assumptions!$B$45*(1-Assumptions!$B$49)-MAX(0,E68*(1-5*Assumptions!$B$50)) -> 7260724 | M68: =IFERROR(IRR(G68:L68),0) -> 0.051575671
A69: Scenario B 4-3 | B69: =$B48 -> 0.7 | C69: =E$44 -> 0.07 | D69: ='Sources & Uses'!$B$7 -> 18818150 | E69: =D69*B69 -> 13172705 | F69: =D69*(1+Assumptions!$B$48)-E69 -> 5927717.2 | G69: =-F69 -> -5927717.2 | H69: ='5Y Underwriting'!C18-MAX(0,E69*(1-(1-1)*Assumptions!$B$50))*C69-MIN(MAX(0,E69*(1-(1-1)*Assumptions!$B$50)),E69*Assumptions!$B$50) -> -76033.1 | I69: ='5Y Underwriting'!D18-MAX(0,E69*(1-(2-1)*Assumptions!$B$50))*C69-MIN(MAX(0,E69*(1-(2-1)*Assumptions!$B$50)),E69*Assumptions!$B$50) -> -59714.988 | J69: ='5Y Underwriting'!E18-MAX(0,E69*(1-(3-1)*Assumptions!$B$50))*C69-MIN(MAX(0,E69*(1-(3-1)*Assumptions!$B$50)),E69*Assumptions!$B$50) -> -42910.868 | K69: ='5Y Underwriting'!F18-MAX(0,E69*(1-(4-1)*Assumptions!$B$50))*C69-MIN(MAX(0,E69*(1-(4-1)*Assumptions!$B$50)),E69*Assumptions!$B$50) -> -25608.734 | L69: ='5Y Underwriting'!G18-MAX(0,E69*(1-(5-1)*Assumptions!$B$50))*C69-MIN(MAX(0,E69*(1-(5-1)*Assumptions!$B$50)),E69*Assumptions!$B$50)+'5Y Underwriting'!$G$16*Assumptions!$B$45*(1-Assumptions!$B$49)-MAX(0,E69*(1-5*Assumptions!$B$50)) -> 7128997 | M69: =IFERROR(IRR(G69:L69),0) -> 0.031010501
A70: Scenario B 4-4 | B70: =$B48 -> 0.7 | C70: =F$44 -> 0.08 | D70: ='Sources & Uses'!$B$7 -> 18818150 | E70: =D70*B70 -> 13172705 | F70: =D70*(1+Assumptions!$B$48)-E70 -> 5927717.2 | G70: =-F70 -> -5927717.2 | H70: ='5Y Underwriting'!C18-MAX(0,E70*(1-(1-1)*Assumptions!$B$50))*C70-MIN(MAX(0,E70*(1-(1-1)*Assumptions!$B$50)),E70*Assumptions!$B$50) -> -207760.15 | I70: ='5Y Underwriting'!D18-MAX(0,E70*(1-(2-1)*Assumptions!$B$50))*C70-MIN(MAX(0,E70*(1-(2-1)*Assumptions!$B$50)),E70*Assumptions!$B$50) -> -191442.04 | J70: ='5Y Underwriting'!E18-MAX(0,E70*(1-(3-1)*Assumptions!$B$50))*C70-MIN(MAX(0,E70*(1-(3-1)*Assumptions!$B$50)),E70*Assumptions!$B$50) -> -174637.92 | K70: ='5Y Underwriting'!F18-MAX(0,E70*(1-(4-1)*Assumptions!$B$50))*C70-MIN(MAX(0,E70*(1-(4-1)*Assumptions!$B$50)),E70*Assumptions!$B$50) -> -157335.78 | L70: ='5Y Underwriting'!G18-MAX(0,E70*(1-(5-1)*Assumptions!$B$50))*C70-MIN(MAX(0,E70*(1-(5-1)*Assumptions!$B$50)),E70*Assumptions!$B$50)+'5Y Underwriting'!$G$16*Assumptions!$B$45*(1-Assumptions!$B$49)-MAX(0,E70*(1-5*Assumptions!$B$50)) -> 6997269.9 | M70: =IFERROR(IRR(G70:L70),0) -> 0.010508228
A71: Scenario B 4-5 | B71: =$B48 -> 0.7 | C71: =G$44 -> 0.09 | D71: ='Sources & Uses'!$B$7 -> 18818150 | E71: =D71*B71 -> 13172705 | F71: =D71*(1+Assumptions!$B$48)-E71 -> 5927717.2 | G71: =-F71 -> -5927717.2 | H71: ='5Y Underwriting'!C18-MAX(0,E71*(1-(1-1)*Assumptions!$B$50))*C71-MIN(MAX(0,E71*(1-(1-1)*Assumptions!$B$50)),E71*Assumptions!$B$50) -> -339487.2 | I71: ='5Y Underwriting'!D18-MAX(0,E71*(1-(2-1)*Assumptions!$B$50))*C71-MIN(MAX(0,E71*(1-(2-1)*Assumptions!$B$50)),E71*Assumptions!$B$50) -> -323169.09 | J71: ='5Y Underwriting'!E18-MAX(0,E71*(1-(3-1)*Assumptions!$B$50))*C71-MIN(MAX(0,E71*(1-(3-1)*Assumptions!$B$50)),E71*Assumptions!$B$50) -> -306364.97 | K71: ='5Y Underwriting'!F18-MAX(0,E71*(1-(4-1)*Assumptions!$B$50))*C71-MIN(MAX(0,E71*(1-(4-1)*Assumptions!$B$50)),E71*Assumptions!$B$50) -> -289062.83 | L71: ='5Y Underwriting'!G18-MAX(0,E71*(1-(5-1)*Assumptions!$B$50))*C71-MIN(MAX(0,E71*(1-(5-1)*Assumptions!$B$50)),E71*Assumptions!$B$50)+'5Y Underwriting'!$G$16*Assumptions!$B$45*(1-Assumptions!$B$49)-MAX(0,E71*(1-5*Assumptions!$B$50)) -> 6865542.9 | M71: =IFERROR(IRR(G71:L71),0) -> -0.009929784
A72: Scenario B 5-1 | B72: =$B49 -> 0.75 | C72: =C$44 -> 0.05 | D72: ='Sources & Uses'!$B$7 -> 18818150 | E72: =D72*B72 -> 14113612 | F72: =D72*(1+Assumptions!$B$48)-E72 -> 4986809.8 | G72: =-F72 -> -4986809.8 | H72: ='5Y Underwriting'!C18-MAX(0,E72*(1-(1-1)*Assumptions!$B$50))*C72-MIN(MAX(0,E72*(1-(1-1)*Assumptions!$B$50)),E72*Assumptions!$B$50) -> 140375.62 | I72: ='5Y Underwriting'!D18-MAX(0,E72*(1-(2-1)*Assumptions!$B$50))*C72-MIN(MAX(0,E72*(1-(2-1)*Assumptions!$B$50)),E72*Assumptions!$B$50) -> 156693.74 | J72: ='5Y Underwriting'!E18-MAX(0,E72*(1-(3-1)*Assumptions!$B$50))*C72-MIN(MAX(0,E72*(1-(3-1)*Assumptions!$B$50)),E72*Assumptions!$B$50) -> 173497.86 | K72: ='5Y Underwriting'!F18-MAX(0,E72*(1-(4-1)*Assumptions!$B$50))*C72-MIN(MAX(0,E72*(1-(4-1)*Assumptions!$B$50)),E72*Assumptions!$B$50) -> 190799.99 | L72: ='5Y Underwriting'!G18-MAX(0,E72*(1-(5-1)*Assumptions!$B$50))*C72-MIN(MAX(0,E72*(1-(5-1)*Assumptions!$B$50)),E72*Assumptions!$B$50)+'5Y Underwriting'!$G$16*Assumptions!$B$45*(1-Assumptions!$B$49)-MAX(0,E72*(1-5*Assumptions!$B$50)) -> 6404498.2 | M72: =IFERROR(IRR(G72:L72),0) -> 0.076046473
A73: Scenario B 5-2 | B73: =$B49 -> 0.75 | C73: =D$44 -> 0.06 | D73: ='Sources & Uses'!$B$7 -> 18818150 | E73: =D73*B73 -> 14113612 | F73: =D73*(1+Assumptions!$B$48)-E73 -> 4986809.8 | G73: =-F73 -> -4986809.8 | H73: ='5Y Underwriting'!C18-MAX(0,E73*(1-(1-1)*Assumptions!$B$50))*C73-MIN(MAX(0,E73*(1-(1-1)*Assumptions!$B$50)),E73*Assumptions!$B$50) -> -760.5 | I73: ='5Y Underwriting'!D18-MAX(0,E73*(1-(2-1)*Assumptions!$B$50))*C73-MIN(MAX(0,E73*(1-(2-1)*Assumptions!$B$50)),E73*Assumptions!$B$50) -> 15557.612 | J73: ='5Y Underwriting'!E18-MAX(0,E73*(1-(3-1)*Assumptions!$B$50))*C73-MIN(MAX(0,E73*(1-(3-1)*Assumptions!$B$50)),E73*Assumptions!$B$50) -> 32361.732 | K73: ='5Y Underwriting'!F18-MAX(0,E73*(1-(4-1)*Assumptions!$B$50))*C73-MIN(MAX(0,E73*(1-(4-1)*Assumptions!$B$50)),E73*Assumptions!$B$50) -> 49663.866 | L73: ='5Y Underwriting'!G18-MAX(0,E73*(1-(5-1)*Assumptions!$B$50))*C73-MIN(MAX(0,E73*(1-(5-1)*Assumptions!$B$50)),E73*Assumptions!$B$50)+'5Y Underwriting'!$G$16*Assumptions!$B$45*(1-Assumptions!$B$49)-MAX(0,E73*(1-5*Assumptions!$B$50)) -> 6263362.1 | M73: =IFERROR(IRR(G73:L73),0) -> 0.050122726
A74: Scenario B 5-3 | B74: =$B49 -> 0.75 | C74: =E$44 -> 0.07 | D74: ='Sources & Uses'!$B$7 -> 18818150 | E74: =D74*B74 -> 14113612 | F74: =D74*(1+Assumptions!$B$48)-E74 -> 4986809.8 | G74: =-F74 -> -4986809.8 | H74: ='5Y Underwriting'!C18-MAX(0,E74*(1-(1-1)*Assumptions!$B$50))*C74-MIN(MAX(0,E74*(1-(1-1)*Assumptions!$B$50)),E74*Assumptions!$B$50) -> -141896.63 | I74: ='5Y Underwriting'!D18-MAX(0,E74*(1-(2-1)*Assumptions!$B$50))*C74-MIN(MAX(0,E74*(1-(2-1)*Assumptions!$B$50)),E74*Assumptions!$B$50) -> -125578.51 | J74: ='5Y Underwriting'!E18-MAX(0,E74*(1-(3-1)*Assumptions!$B$50))*C74-MIN(MAX(0,E74*(1-(3-1)*Assumptions!$B$50)),E74*Assumptions!$B$50) -> -108774.39 | K74: ='5Y Underwriting'!F18-MAX(0,E74*(1-(4-1)*Assumptions!$B$50))*C74-MIN(MAX(0,E74*(1-(4-1)*Assumptions!$B$50)),E74*Assumptions!$B$50) -> -91472.259 | L74: ='5Y Underwriting'!G18-MAX(0,E74*(1-(5-1)*Assumptions!$B$50))*C74-MIN(MAX(0,E74*(1-(5-1)*Assumptions!$B$50)),E74*Assumptions!$B$50)+'5Y Underwriting'!$G$16*Assumptions!$B$45*(1-Assumptions!$B$49)-MAX(0,E74*(1-5*Assumptions!$B$50)) -> 6122225.9 | M74: =IFERROR(IRR(G74:L74),0) -> 0.024312877
A75: Scenario B 5-4 | B75: =$B49 -> 0.75 | C75: =F$44 -> 0.08 | D75: ='Sources & Uses'!$B$7 -> 18818150 | E75: =D75*B75 -> 14113612 | F75: =D75*(1+Assumptions!$B$48)-E75 -> 4986809.8 | G75: =-F75 -> -4986809.8 | H75: ='5Y Underwriting'!C18-MAX(0,E75*(1-(1-1)*Assumptions!$B$50))*C75-MIN(MAX(0,E75*(1-(1-1)*Assumptions!$B$50)),E75*Assumptions!$B$50) -> -283032.75 | I75: ='5Y Underwriting'!D18-MAX(0,E75*(1-(2-1)*Assumptions!$B$50))*C75-MIN(MAX(0,E75*(1-(2-1)*Assumptions!$B$50)),E75*Assumptions!$B$50) -> -266714.64 | J75: ='5Y Underwriting'!E18-MAX(0,E75*(1-(3-1)*Assumptions!$B$50))*C75-MIN(MAX(0,E75*(1-(3-1)*Assumptions!$B$50)),E75*Assumptions!$B$50) -> -249910.52 | K75: ='5Y Underwriting'!F18-MAX(0,E75*(1-(4-1)*Assumptions!$B$50))*C75-MIN(MAX(0,E75*(1-(4-1)*Assumptions!$B$50)),E75*Assumptions!$B$50) -> -232608.38 | L75: ='5Y Underwriting'!G18-MAX(0,E75*(1-(5-1)*Assumptions!$B$50))*C75-MIN(MAX(0,E75*(1-(5-1)*Assumptions!$B$50)),E75*Assumptions!$B$50)+'5Y Underwriting'!$G$16*Assumptions!$B$45*(1-Assumptions!$B$49)-MAX(0,E75*(1-5*Assumptions!$B$50)) -> 5981089.8 | M75: =IFERROR(IRR(G75:L75),0) -> -0.0013800009
A76: Scenario B 5-5 | B76: =$B49 -> 0.75 | C76: =G$44 -> 0.09 | D76: ='Sources & Uses'!$B$7 -> 18818150 | E76: =D76*B76 -> 14113612 | F76: =D76*(1+Assumptions!$B$48)-E76 -> 4986809.8 | G76: =-F76 -> -4986809.8 | H76: ='5Y Underwriting'!C18-MAX(0,E76*(1-(1-1)*Assumptions!$B$50))*C76-MIN(MAX(0,E76*(1-(1-1)*Assumptions!$B$50)),E76*Assumptions!$B$50) -> -424168.88 | I76: ='5Y Underwriting'!D18-MAX(0,E76*(1-(2-1)*Assumptions!$B$50))*C76-MIN(MAX(0,E76*(1-(2-1)*Assumptions!$B$50)),E76*Assumptions!$B$50) -> -407850.76 | J76: ='5Y Underwriting'!E18-MAX(0,E76*(1-(3-1)*Assumptions!$B$50))*C76-MIN(MAX(0,E76*(1-(3-1)*Assumptions!$B$50)),E76*Assumptions!$B$50) -> -391046.64 | K76: ='5Y Underwriting'!F18-MAX(0,E76*(1-(4-1)*Assumptions!$B$50))*C76-MIN(MAX(0,E76*(1-(4-1)*Assumptions!$B$50)),E76*Assumptions!$B$50) -> -373744.51 | L76: ='5Y Underwriting'!G18-MAX(0,E76*(1-(5-1)*Assumptions!$B$50))*C76-MIN(MAX(0,E76*(1-(5-1)*Assumptions!$B$50)),E76*Assumptions!$B$50)+'5Y Underwriting'!$G$16*Assumptions!$B$45*(1-Assumptions!$B$49)-MAX(0,E76*(1-5*Assumptions!$B$50)) -> 5839953.7 | M76: =IFERROR(IRR(G76:L76),0) -> -0.026953081
A80: Scenario grid assumptions reflect annual distributions, debt amortization, interest and an exit at year 5.
A81: The two matrices are independent; they hold all other assumptions constant at Assumptions values.
A82: A: entry / exit price; B: leverage / borrowing cost; figures are illustrative.
